{"am":{"w":"AM","p":"æm","t":"be的单数第一人称\\n[计] 存取管理程序, 寻址方式, 地址标记, 变址数, 调幅, 辅助存储器"},"ama":{"w":"AMA","p":"'ɑ:mɑ:","t":"[计] 相联存储器阵列, 故障自动分析, 自动报文计价\\n[医] 半规管膨隆(在壶腹对侧)"},"amaas":{"p":"'æmɑ:s","t":"(=alastrim)乳白痘, 类天花"},"amabel":{"w":"Amabel","p":"'æmәbel","t":"阿玛贝尔(女子名)"},"amabile":"阿马比尔（人名）","amable":"n. (Amable)人名；(法)阿马布勒；(英)阿玛布尔；(西)阿马夫莱","amac":"abbr. alternative macrophage activation-associated CC chemokine 选择性巨噬细胞激活作用相关的CC趋化因子","amacher":"[人名] 阿马彻","amacker":"[人名] 阿马克","amacratie":"[医] 焦聚的","amacrinal":"[医] 无长突的","amacrine":"[医] 无长突的(神经细胞), 无长突细胞","amad":"n. (Amad)人名；(阿拉伯)阿马德","amada":"abbr. 日本天田公司","amadavat":{"p":",æmәdә'væt","t":"n. [动] 莓莺(产于印度的观赏鸟),梅花雀"},"amadeo":"n. (Amadeo)人名；(英、西、葡)阿马德奥","amadeu":"n. (Amadeu)人名；(葡)阿马德乌","amadeus":{"w":"Amadeus","p":"a'madiəs","t":"n. 莫扎特（奥地利作曲家）；莫扎特传（电影名）；阿玛迪斯（唱片公司品牌）"},"amadi":"n. (Amadi)人名；(阿拉伯)阿马迪","amadin":"[医] 阿马丁(苦扁桃中的一种球蛋白)","amadinone":"阿马地酮","amadis":{"p":"'æmədis","t":"n. 阿玛迪斯（英雄之象征）"},"amado":"阿玛多(巴西作家)","amador":"n. (Amador)人名；(法、西、葡)阿马多尔","amadou":{"p":"'æmәdu:","t":"n. 火绒(止血和引火用)"},"amae":{"p":"ɑ:'meɪ","t":"[医]（单ama）半规管膨隆（在壶腹对侧）"},"amaesthetic":"n. 麻醉剂","amaethon":{"w":"Amaethon","t":"[网络] 神农氏"},"amafolone":"阿马夫隆","amagansett":"阿默甘西特（人名）","amagasaki":{"w":"Amagasaki","p":",æmә^ә'sɑ:ki","t":"尼崎[日本本州岛西南部城市]"},"amagat":"阿马伽","amager":"[地名] [丹麦] 阿迈厄岛","amah":{"p":"'ɑ:mә","t":"n. 奶妈, 保姆, 女仆"},"amahs":{"p":"'ɑːmə","t":"n. 奶妈；保姆；女仆（印度等一些东方国家的奶妈）\\nn. (Amah)人名；(多哥)阿马"},"amain":{"p":"ә'mein","t":"adv. 全力地, 全速地, 急速地, 突然"},"amaiosis":"不减数分裂","amakebe":"[医] 乌干达犊梨浆虫病","amakinite":"羟铁矿","amakrine":"[医] 无长突的(神经细胞), 无长突细胞","amakusa":"日本的一种瓷石","amal":{"w":"AMAL","t":"[医] 航空医学加速实验室"},"amalek":{"p":"'æməlek","t":"n. 亚玛力人"},"amalekite":{"w":"Amalekite","p":"ә'mælәkait","t":"n. 亚玛力人(基督教《圣经》所载出埃及前后生活在迦南南部一带的一游牧部落成员)"},"amalekites":{"p":"ə'mæləkait","t":"n. 亚玛力人"},"amalfi":{"w":"Amalfi","t":"n. (Amalfi)人名；(西)阿马尔菲"},"amalgam":{"p":"ә'mælgәm","t":"n. 汞合金, 汞齐\\n[化] 汞齐; 汞合金"},"amalgamable":{"p":"ә'mæl^әmәbl","t":"a. 可合汞的, 可成合金的, 可以混合的"},"amalgamate":{"p":"ә'mælgәmeit","t":"v. 使汞齐化, 合并"},"amalgamated":{"w":"Amalgamated","t":"合并\\n混合\\n（使）汞齐化（ amalgamate的过去式和过去分词 ）"},"amalgamates":{"p":"əˈmælgəˌmeɪts","t":"n. （使）（金属）汞齐化( amalgamate的名词复数 ); （使）合并; 联合; 结合\\nv. （使）（金属）汞齐化( amalgamate的第三人称单数 ); （使）合并; 联合; 结合"},"amalgamating":"[化] 汞齐化的; 汞齐化; 汞齐化作用","amalgamation":{"p":"ә.mælgә'meiʃәn","t":"n. 汞齐化, 合并\\n[化] 汞齐化; 汞齐化作用; 混汞法"},"amalgamations":"(amalgamation 的复数) n. 汞齐化, 合并\\n[化] 汞齐化; 汞齐化作用; 混汞法","amalgamative":{"p":"ә'mælgәmeitiv","t":"a. 合并的, 汞齐的"},"amalgamator":{"p":"ә'mælgәmeitә","t":"n. 合并者, 混汞提金器\\n[化] 拌和机; 混合机; 搅拌机"},"amalgams":{"p":"əˈmælgəmz","t":"n. 汞合金( amalgam的复数形式 ); 混合物"},"amalia":{"p":"ə'meiljə","t":"n. 阿玛莉亚（女子名）"},"amalie":"[机] 阿美来","amalog":{"w":"Amalog","t":"阿马洛格镍铬钨合金"},"amalosis":"[医] 不减数分裂","amalthea":{"w":"Amalthea","p":",æmәl'θi:ә","t":"[天]木卫五(靠木星最近的卫星)"},"amalya":"[人名] 阿马利亚，阿玛莉娅（女名）","amamee":{"w":"Amamee","t":"阿马米平纹织物"},"aman":"n. [圣经]哈曼（波斯王亚哈随鲁的宰相, 阴谋杀死所有犹太人, 等于Haman）","amana":"n. (Amana)人名；(法)阿马纳","amanar":"n. (Amanar)人名；(罗)阿默讷尔","amancio":"n. (Amancio)人名；(西、葡)阿曼西奥","amand":"阿曼德（姓氏）","amanda":{"p":"ә'mændә","t":"n. 阿曼达（女子名）"},"amandes":"杏仁；果仁","amandin":"[化] 苦杏仁球蛋白\\n[医] 阿曼丁, 苦扁桃仁球蛋白","amandine":{"p":",ɑːmən'diːn","t":"n. (Amandine)人名；(法)阿芒迪娜\\na. 含有杏仁的"},"amani":"n. 阿玛尼（时装品牌）\\nn. (Amani)人名；(法、俄、阿富、刚(金)、坦桑)阿马尼","amaning":{"p":"'eimən","t":"n. 【杜埃版《圣经》】= Haman"},"amanita":{"p":",æmә'naitә","t":"n. [植]伞形毒菌"},"amanitas":{"p":"æmə'nɪ:tə","t":"n. 伞形毒菌；毒蕈之一种"},"amanitatoxin":"[医] 蝇蕈毒素, 鹅膏毒素","amanitin":{"p":",æmә'ni:tin","t":"n. [生化]蝇蕈素"},"amanitine":"[化] 鹅膏蕈碱; 鹅膏蕈素\\n[医] 蝇蕈素, 鹅膏素","amanitotoxin":"[医] 蝇蕈毒素, 鹅膏毒素","amann":"n. (Amann)人名；(德、法、西、葡、英、瑞典)阿曼","amanozine":"[化] 阿马诺嗪","amanpour":"n. (Amanpour)人名；(英)阿曼普尔","amant":"n. (Amant)人名；(法)阿芒","amantadine":{"p":"ә'mæntәdi:n","t":"[药]金刚(烷)胺,三环癸胺(抗病毒药)"},"amantes":"n. (Amantes)人名；(西)阿曼特斯","amanthophilous":"喜原野的","amanuenses":"n. 抄写员；文书助理 (amanuensis的变形)","amanuensis":{"p":"ә.mænju'ensis","t":"n. 笔记者, 抄写员, 书记"},"amanullah":"n. (Amanullah)人名；(阿富、伊朗、巴基)阿马努拉","amap":{"p":"ə'mæp","t":"abbr. advanced multiprogramming-analysis 高级多种编程分析"},"amar":"n. 艾玛尔（人名）","amara":"[医] 苦味药","amaral":"n. (Amaral)人名；(西、葡、东帝)阿马拉尔","amarantaceae":{"w":"Amarantaceae","t":"[医] 苋科"},"amarante":"n. (Amarante)人名；(西、意、葡)阿马兰特","amaranth":{"p":"'æmәrænθ","t":"n. 不凋花, 苋属植物, 紫红色\\n[化] 苋菜红"},"amaranthaceae":{"w":"Amaranthaceae","t":"苋科; 苋科"},"amaranthine":{"p":".æmә'rænθain","t":"a. 不凋的, 不死的, 紫红的"},"amaranths":"(amaranth 的复数) n. 不凋花, 苋属植物, 紫红色\\n[化] 苋菜红","amaranthus":{"p":",æmə'rænθəs","t":"n. [植] 苋属；苋属植物；雁来红"},"amarantite":"[化] 红铁矾","amarapura":"[地名] [缅甸] 阿马拉布拉","amarasterone":"苋菜甾酮; 苋菜甾酮","amarbeline":"[机] 苦杏贝灵","amarbital":"[化] 苯基·乙基巴比土酸","amarcord":"[电影]阿玛柯德","amare":"n. (Amare)人名；(西、埃塞)阿马雷","amarelle":{"p":",æmә'rel","t":"n. [植]酸樱桃"},"amaretti":"意大利杏仁味小饼干","amaretto":{"p":",æmә'retәj","t":"n. 意大利苦杏酒"},"amargosa":{"p":",æmә'^әusә","t":"(=azadarach, azadarichta)苦楝树皮"},"amargosite":{"p":"ә'mɑ:^әsait","t":"膨土岩"},"amari":"n. (Amari)人名；(法、意、阿拉伯)阿马里；(英)阿马里，阿玛丽(女名)","amaril":"[医] 阿马里耳, 黄热病毒质(过去认为本品系致黄热病的毒质)","amarillic":"[医] 阿马里耳毒质的","amarillite":"黄铁钠矾","amarillo":{"p":",æmə'riləu","t":"n. 阿马里洛（美国城市）"},"amarin":"[化] 苦杏精; 2,4,5-三苯基咪唑啉","amarine":"[化] 苦杏精; 2,4,5-三苯基咪唑啉\\n[医] 苦杏素, 苦木精","amarna":{"p":"ə'mɑ:nə","t":"n. （古埃及）阿马尔那；阿玛那"},"amaro":"n. (Amaro)人名；(法、西、意、葡)阿马罗","amarogentin":"[化] 苦杏苷","amaroid":"[医] 苦味质","amaroidal":"[医] 苦味质的","amarolide":"[化] 臭椿苦内酯","amaromycin":"[化] 苦味霉素\\n[医] 苦味霉素","amaron":"[化] 苦杏碱; 四苯基吡嗪","amarthritis":"[医] 多数关节炎","amarum":"[医] 苦味药","amarylism":"[医] 黄热病","amaryllidaceae":{"w":"Amaryllidaceae","t":"[医] 石蒜科"},"amaryllidaceous":{"p":",æmə,rɪlɪ'deɪʃəs","t":"a. 属石蒜科的"},"amaryllis":{"p":".æmә'rilis","t":"n. 孤挺花"},"amas":{"w":"Amas","t":"(AMA 的复数) [计] 相联存储器阵列, 故障自动分析, 自动报文计价\\n[医] 半规管膨隆(在壶腹对侧)"},"amasa":{"p":"ə'meisə","t":"n. 亚玛撒（圣经中的人物）"},"amasesis":"[医] 咀嚼不能","amasi":"酸牛奶","amasia":"[地名] [亚美尼亚] 阿马西亚; [地名] [土耳其] 阿马西亚","amass":{"p":"ә'mæs","t":"vt. 积聚, 堆积"},"amassable":"a. amass的变形","amassed":{"p":"ə'mæs","t":"vt. 积聚, 积累"},"amasser":"n. amass的变形","amasses":{"p":"əˈmæsiz","t":"v. 积累, 积聚( amass的第三人称单数 )"},"amassette":{"p":",æmә'set","t":"[法]古代及中世纪 在绘画中用于调色的刀状工具(用兽角制成), 刮刀"},"amassing":"n. 积聚；积累","amassment":{"p":"ә'mæsmәnt","t":"n. 积蓄, 聚积"},"amasthenic":"[医] 焦聚的","amastia":{"p":"ә'mæstiә","t":"乳腺缺乏, 无乳房(畸形)"},"amastigote":"无鞭毛体","amat":"n. (Amat)人名；(法)阿马；(西、阿拉伯)阿马特；(中)艾买提(维吾尔·汉语拼音)","amatagati":"[网络] 阿马塔加蒂","amate":{"p":"ә'meit","t":"vt. [古]使懊恼；使挫折"},"amaterasu":{"p":"'ɑ:mɑ:te'rɑ:su","t":"n. 天照大神；太阳女神（日本神话中高天原的统治者）"},"amates":"(amate 的第三人称 -s形式) vt. [古]使懊恼；使挫折","amateur":{"p":"'æmәtә","t":"n. 业余爱好者, 外行, 爱好者\\n[电] 业余家"},"amateurish":{"p":".æmә'tә:riʃ","t":"a. 业余的, 外行的, 不熟练的"},"amateurishly":{"p":"ˈæmətərɪʃlɪ","t":"adv. 外行地, 生手地"},"amateurishness":"n. amateurish的变形","amateurism":{"p":"'æmәtә:rizm","t":"n. 外行做法, 业余身份"},"amateurs":"n. 业余爱好者；非专业人员（amateur的复数）","amateurship":{"p":",æmə'tɜːʃɪp","t":"n. 资格；业余者的资格或身份"},"amathophobia":"[医] 飞尘恐怖","amati":{"w":"Amati","p":"ə'mɑ:ti","t":"n. 阿玛蒂提琴"},"amatis":{"p":"ə'mɑ:ti","t":"n. 阿玛蒂提琴"},"amative":{"p":"'æmәtiv","t":"a. 恋爱的, 好色的"},"amatively":{"p":"'æmətɪvlɪ","t":"adv. 恋爱地, 好色地"},"amativeness":"[医] 恋爱嗜好, 好色","amato":{"w":"Amato","t":"n. (Amato)人名；(法、西、意、葡)阿马托；(日)天户(姓)"},"amatol":{"p":"'æmәtɒl","t":"n. 阿马托炸药\\n[化] 额马突(硝铵、三硝基甲苯炸药)"},"amatorial":{"p":"'æmətəri, ,æmə'tɔ:riəl, ,æmə'tɔ:riəs","t":"a. 恋爱的；好色的"},"amatorially":{"p":",æmə'tɔ:riəli","t":"adv. amatory, amatorial, amatorious的变形"},"amatorious":{"p":"'æmətəri; ,æmə'tɔ:riəl; ,æmə'tɔ:riəs","t":"a. 恋人的；恋爱的, (表示或引起)爱情的, (表示)性爱的, 求爱的(尤指性爱)；色情的"},"amatory":{"p":"'æmәtәri","t":"a. 恋爱的, 情人的\\n[医] 恋爱的, 性欲的"},"amau":"n. (Amau)人名；(日)天羽(姓)","amaurosis":{"p":".æmɒ:'rәusis","t":"n. 黑朦\\n[医] 黑蒙"},"amaurotic":"[医] 黑蒙的","amaury":"阿莫里（人名）","amausite":{"p":"'æmɔ:sait","t":"燧石"},"amax":{"w":"AMAX","t":"[计] 一种管理信件暂存区的工具程序"},"amaxophobia":{"p":"ә,mæksә'fәubjә","t":"乘车恐怖"},"amaya":"阿马亚（菲律宾）","amayas":"阿马亚（菲律宾）","amaz":"abbr. Amazonas 亚马逊（巴西州名）","amazake":"日本甘酒","amaze":{"p":"ә'meiz","t":"vt. 使吃惊"},"amazed":{"p":"ә'meizd","t":"a. 吃惊的, 惊奇的"},"amazedly":{"p":"ә'meizidli","t":"adv. 吃惊地, 惊奇地"},"amazedness":{"p":"ə'meizidnis","t":"n. amazed的变形"},"amazement":{"p":"ә'meizmәnt","t":"n. 惊愕, 惊异"},"amazements":"(amazement 的复数) n. 惊愕, 惊异","amazes":{"p":"əˈmeiziz","t":"v. 使大为吃惊, 使惊奇( amaze的第三人称单数 )"},"amazia":"[医] 无乳腺[畸形]","amazinc":{"w":"Amazinc","p":"ә'meiziŋk","t":"高效富锌防锈涂料"},"amazing":{"p":"ә'meiziŋ","t":"a. 令人惊异的"},"amazingly":"adv. 令人惊讶地；惊奇地","amazon":{"p":"'æmәzɒn","t":"n. 亚马孙河\\n[医] 无乳腺者"},"amazona":"[医]亚马逊鹦鹉","amazonas":{"w":"Amazonas","p":",æmә'zәunәs","t":"亚马孙(巴西州名)"},"amazone":"n. 刚果绿；亚马孙","amazonia":"n. 亚马孙古陆, 亚马孙流域","amazonian":{"w":"Amazonian","p":",æmә'zәunjәn","t":"n. 亚马逊河区的印第安人\\na. 亚马逊河的, (女子)刚勇好战的,有男子气的"},"amazonians":{"p":",æmə'zəunjən","t":"adj. （女子）刚勇的"},"amazonite":{"p":"'æmәzәnait","t":"n. 天河石, 绿长石"},"amazons":"n. 奴役现象；亚马逊人；亚马逊鹦鹉；亚马逊女战士（Amazon的复数）","amazonstone":{"p":"'æməzənstəʊn","t":"天河石"},"amazonukkah":{"w":"Amazonukkah","t":null},"amb":"高级内存缓冲器（Advanced Memory Buffer）","amba":{"p":"'æmbә","t":"n. 安巴（抽穗早型鸭茅品种）"},"ambac":"abbr. American Bosch Anna Corporation 美国博施·阿马公司; American Municipal Bond Assurance Corporation 美国市政债券保险公司; Associate Member of the British Association of Chemists 英国药剂师协会准会员","ambach":{"p":"'æmbætʃ","t":"n. = ambatch"},"ambage":{"p":"'æmbɪdʒ","t":"n. 模棱两可, 迂回的说法, 间接的说法"},"ambages":{"p":"æm'beidʒi:z","t":"n. 拐弯抹角, 诡秘的行动"},"ambagious":{"p":"æm'beidʒәs","t":"a. 迂远的, 迂曲的"},"ambam":"[化] 代森铵","ambanja":"[地名] [马达加斯加] 安班扎","ambar":"n. 淡而无味\\nn. (Ambar)人名；(阿拉伯、葡)安巴尔","ambargris":"[化] 龙涎香","ambary":{"p":"æm'bɑ:ri","t":"n. 洋麻"},"ambas":{"p":"'æmbə","t":"n. = anba"},"ambassa":"n. (Ambassa)人名；(法)安巴萨","ambassade":{"p":",æmbə'seid, 'æmbəseid","t":"n. 大使馆"},"ambassador":{"p":"æm'bæsәdә","t":"n. 大使\\n[法] 大使, 使节, 代理"},"ambassadorial":{"p":"æm.bæsә'dɒ:riәl","t":"a. 大使的, 大使一级的\\n[法] 大使的, 使节的"},"ambassadors":{"p":"æmˈbæsədəz","t":"n. 大使( ambassador的复数形式 ); （派驻联合国等国际组织的）代表; 特使; [比喻]使者"},"ambassadorship":{"p":"æm'bæsәdәʃip","t":"n. 大使的职位"},"ambassadorships":{"p":"æm'bæsədəʃip","t":"n. 大使的职位"},"ambassadress":{"p":"æm'bæsәdris","t":"n. 大使夫人, 女大使\\n[法] 女大使, 大使夫人"},"ambassage":{"p":"'æmbəsɪdʒ","t":"n. = embassage"},"ambassy":{"p":"'æmbəsɪ","t":"n. = embassy"},"ambatch":{"p":"'æmbætʃ","t":"n. [植]田皂角(产于非洲,木质轻软)"},"ambato":{"w":"Ambato","t":"安巴托(厄瓜多尔)"},"ambatoarinite":"碳酸锶铈矿","ambazone":"[化] 安巴腙","ambe":"abbr. advanced multi-band excitation (vocoder) 高级多频段激励（声码器）","ambedkar":"n. (Ambedkar)人名；(英、印)安贝德卡","ambeer":{"p":"'æmbiә(r)","t":"n. 烟草汁"},"ambelline":{"p":"'æmbilin","t":"安贝灵, 颠茄朱顶兰碱"},"ambenonium":"[医] 阿苯铵","amber":{"p":"'æmbә","t":"n. 琥珀, 琥珀色\\na. 琥珀色的, 琥珀似的"},"amberbell":"[网络] 安贝","amberboa":{"w":"Amberboa","t":"[网络] 珀菊属"},"ambercane":{"p":"'æmbәkein","t":"南非蜀黍"},"ambered":{"p":"'æmbə","t":"a. 琥珀色的；琥珀制的\\nn. 琥珀；琥珀色\\nvt. 使呈琥珀色"},"amberfish":{"p":"'æmbәfiʃ","t":"n. [鱼]鰤"},"amberg":"n. (Amberg)人名；(英)安伯格；(德、法、西)安贝格；(瑞典)安贝里","amberglass":"[化] 琥珀玻璃","ambergris":{"p":"'æmbәgri:s","t":"n. 龙涎香\\n[化] 龙涎香"},"amberina":{"p":"æmbə'ri:nə","t":"n. 美产的一种艺术玻璃"},"amberite":{"p":"'æmbәrait","t":"n. 琥珀炸药,阿比里特炸药(一种无烟炸药)"},"amberjack":{"p":"'æmbәdʒæk","t":"n. 琥珀鱼"},"amberley":{"w":"Amberley","t":"n. (Amberley)人名；(英)安伯利"},"amberlite":{"w":"Amberlite","p":"'æmbәlait","t":"n. 安伯来特(一种离子交换树脂,商标名)"},"amberoid":{"p":"'æmbәrɔid","t":"n. 合成琥珀"},"amberplex":"离子交换膜","ambers":"[化] 褐绉片; 橡胶褐绉片","amberwood":"[化] 酚醛树脂胶合板","ambi":"pref. 表示两边","ambiance":{"p":"'æmbiәns","t":"n. 气氛；周围环境（等于ambience）"},"ambiances":"(ambiance 的复数) n. 气氛；周围环境（等于ambience）","ambicoloration":{"p":",æmbi,kʌlә'reiʃәn","t":"两色(作用), 显两色(作用)"},"ambident":"[化] 两可; 两可的","ambidexter":{"p":".æmbi'dekstә","t":"a. 两手同利的, 两方面皆能的, 搞两面派的\\nn. 两手俱利的人, 技术极高的人, 搞两面派的人"},"ambidexterity":{"p":".æmbidek'steriti","t":"n. 两手俱利, 两面派手法\\n[医] 两手同利"},"ambidexterous":"a. 非常灵巧的, 两面讨好的, 非常熟练的","ambidextral":"a. ambidexter的变形","ambidextrality":"[医] 两手同利","ambidextrism":"[医] 两手同利","ambidextrous":{"p":".æmbi'dekstrәs","t":"a. 两手俱利的, 搞两面派的\\n[医] 两手同利的"},"ambidextrously":"a. 两手同利的","ambidextrousness":"[网络] 双目感","ambien":"n. 安必恩（美国产的一种安眠药）","ambience":{"p":"'æmbiәns","t":"n. 周围环境, 气氛"},"ambiences":"(ambience 的复数) n. 周围环境, 气氛","ambient":{"p":"'æmbiәnt","t":"a. 周围的\\nn. 周围环境"},"ambiguities":"歧义\\n模棱两可","ambiguity":{"p":".æmbi'gju:iti","t":"n. 不明确, 含糊\\n[计] 二义性; 多义性"},"ambiguous":{"p":"æm'bigjuәs","t":"a. 不明确的, 模棱两可的\\n[法] 意思含糊的, 模棱两可的, 暧昧的"},"ambiguously":"adv. 含糊不清地","ambiguousness":{"p":"æm'bigjuəsnis","t":"n. 含混；歧义性"},"ambilateral":"[医] 两侧的","ambilevosity":"[医] 两手不利","ambilevous":"[医] 两手不利的","ambilingual":{"p":",æmbi'liŋ^wәl","t":"a. & n.精通两国语言的(人)"},"ambilobe":"[地名] [马达加斯加] 安比卢贝","ambinon":"[医] 安比农(垂体促性腺激素)","ambiocularity":"[医] 双眼并能(能同等使用两眼)","ambiophony":{"p":",æmbi'ɔfәni","t":"立体混响"},"ambiopia":{"p":"æmbi'әupiә","t":"[拉]复视"},"ambiparous":{"p":",æmbi'pærәs","t":"花叶兼具的"},"ambipharynx":{"p":"'æmbi'færiŋks","t":"围咽膜"},"ambiplasma":{"p":"æmbi'plæzmә","t":"n. 双极性等离子体"},"ambipolar":{"p":"æmbi'pәulә","t":"[电] 双极性的"},"ambisextrous":{"p":",æmbi'sekstrәs","t":"a. 不分男女的,包括男女的,两性的,对两性都有吸引力的"},"ambisexual":{"p":",æmbi'seksjuәl","t":"两性的, 展示或构成男女两性共有的性特性或性特征的"},"ambisexuality":{"p":",æmbi,seksju'æliti","t":"(=ambosexuality)两性(特征)(尤用指行为条件)"},"ambisinister":{"p":",æmbi'sinistә","t":"a. 两手均不灵活的"},"ambisinistrous":{"p":",æmbisi'nistrәs","t":"两手不利的"},"ambisome":"两性霉素b脂质体注射剂","ambisonics":{"p":",æmbi'sɔniks","t":"[复]n.[用作单](使用电子手段加强声波方向性的)高保真度立体声响复制"},"ambisyllabic":{"p":",æmbisi'læbik","t":"a. [语]属二音节的,(辅音)与前后元音都有关系的(如cynic中的n)"},"ambit":{"p":"'æmbit","t":"n. 周围, 范围, 界限, 领域"},"ambitchous":{"w":"Ambitchous","t":null},"ambitendence":"矛盾意志","ambitendency":{"p":".æmbi'tendәnsi","t":"n. 矛盾意向\\n[医] 矛盾意向"},"ambition":{"p":"æm'biʃәn","t":"n. 野心, 志向"},"ambitionless":"a. ambition的变形","ambitions":{"p":"æm'bɪʃənz","t":"n. 抱负( ambition的复数形式 ); 渴望得到的东西; 追求的目标; 夙愿"},"ambitious":{"p":"æm'biʃәs","t":"a. 有野心的, 抱负不凡的, 雄心勃勃的"},"ambitiously":"adv. 雄心勃勃地；劲头十足地；热切地","ambitiousness":{"p":"æm'biʃəs","t":"n. 不凡的抱负"},"ambitus":"[医] 周边","ambivalence":{"p":"æm'bivәlәns","t":"n. 矛盾情绪\\n[医] 矛盾情绪(两种情感互相冲突)"},"ambivalences":"(ambivalence 的复数) n. 矛盾情绪\\n[医] 矛盾情绪(两种情感互相冲突)","ambivalency":"矛盾情绪","ambivalent":{"p":"æm'bivәlәnt","t":"a. 矛盾的, 模棱两可的\\n[医] 矛盾情绪的"},"ambivalently":"adv. 有矛盾感情地","ambiversion":{"p":".æmbi'vә:ʒәn","t":"n. 中间性格\\n[医] 中向人格(介于精神内向和精神外向之间)"},"ambiversive":"a. ambiversion的变形","ambivert":{"p":"'æmbivә:t","t":"n. 中间性格者\\n[医] 中向人格者"},"amble":{"p":"'æmbl","t":"n. 马的缓行步态, 缓行漫步\\nvi. 马缓行, 从容漫步"},"ambled":{"p":"'æmb(ə)l","t":"vi. （马）缓行；从容漫步\\nn. （马的）缓行步态；漫步\\nn. (Amble)人名；(瑞典、挪)安布勒"},"ambler":{"p":"'æmblә","t":"n. 缓行的马, 慢慢走的人"},"ambles":{"p":"ˈæmbəlz","t":"v. （马）缓行( amble的第三人称单数 ); 从容地走, 漫步"},"ambleside":"[地名] [英国] 安布尔赛德","ambling":{"p":"'æmb(ə)l","t":"vi. （马）缓行；从容漫步\\nn. （马的）缓行步态；漫步\\nn. (Amble)人名；(瑞典、挪)安布勒"},"amblingly":"adv. amble的变形","amblings":"(ambling 的复数) vi. （马）缓行；从容漫步\\nn. （马的）缓行步态；漫步\\nn. (Amble)人名；(瑞典、挪)安布勒","ambloma":{"p":"æm'blәumә","t":"[希](=abortion)流产"},"ambloplites":{"w":"Ambloplites","t":"n. 钝棘翻车鱼属\\n[网络] 钝鲈属"},"amblosis":{"p":"æm'blәusis","t":"流产"},"amblotic":{"p":"æm'blɔtik","t":"使流产的, 堕胎的"},"amblyacousia":{"p":",æbliә'ku:siә","t":"听觉迟钝, 弱听"},"amblyaphia":"[医] 触觉迟钝","amblychromasia":{"p":",æblikrә'meiziә","t":"弱染性"},"amblychromatic":{"p":",æblikrә'mætik","t":"弱染的"},"amblygeustia":"[医] 味觉迟钝","amblygonite":{"p":"æm'bli^әnait","t":"n. [矿]锂磷铝石"},"amblykusis":{"p":",æmbli'kju:sis","t":"听觉迟钝"},"amblyomma":{"w":"Amblyomma","t":"[医] 钝眼蜱属"},"amblyope":{"p":"'æmbliәup","t":"弱视者"},"amblyopia":{"p":".æmbli'әupiә","t":"n. 弱视\\n[医] 弱视"},"amblyopiatrics":{"p":",æmbli,әupi'ætriks","t":"弱视矫正法"},"amblyopic":{"p":",æmbli'ɔpik","t":"a. 弱视的"},"amblyopsidae":{"w":"Amblyopsidae","t":"短面鱼科"},"amblyoscope":"[医] 弱视镜","amblypygi":{"w":"Amblypygi","t":"无鞭目"},"amblyrhynchus":{"w":"Amblyrhynchus","t":"n. 钝喙蜥属\\n[网络] 须蜥蜴属；钝嘴鬣蜥属；鬣蜥"},"amblyslegite":"[化] 铁苏辉石","amblystegite":{"p":"æm'blislә,dʒait","t":"铁苏辉"},"amblystoma":{"w":"Amblystoma","t":"[医] 美西螈属"},"ambo":{"p":"'æmbәu","t":"n. 读经台\\n[医] 关节盂缘"},"amboceptoid":{"p":",æmbәu'septɔid","t":"类介体"},"amboceptor":{"p":"'æmbә,septә, -bәu,septә","t":"n. [生]介体,溶血素"},"amboceptorgen":{"p":",æmbә'septәdʒen","t":"介体[抗]原, 双受体原"},"amboina":{"w":"Amboina","p":"æm'bɔinә","t":"n. (印尼)安汶岛"},"amboinese":{"w":"Amboinese","p":",æmbɔi'ni:z","t":"n. (印尼)安汶人(语)"},"amboise":{"p":"ɑ:ŋbwaz","t":"n. 安博瓦兹（法国中西部城镇）"},"ambomalleal":"[医] 砧骨锤骨的","ambomycin":{"p":"æmbәu'maisin","t":"(=duazomycinC)二霉素,偶氮霉素C"},"ambon":"[医] 关节盂缘","ambonese":{"w":"Ambonese","p":",æmbɔi'ni:z; ,æmbə'ni:z","t":"n. (印度尼西亚)安汶岛岛民；安汶岛岛民的语言\\na. 安汶岛的；安汶岛岛民的"},"ambos":"[医] 砧骨","ambosexual":"[医] 两性的","ambosexuality":"[医] 两性[特征](如半阴阳等)","ambotoxoid":{"p":"'æmbәu'tɔksɔid","t":"(葡萄)球菌类毒素, 综合类毒素"},"amboy":"[地名] [美国] 安博伊","amboyna":{"p":"æm'bɔinә","t":"n. (=amboina)青龙木,黄柏木"},"ambra":"[医] 琥珀","ambrac":{"w":"Ambrac","p":"'æmbræk","t":"阿莫布拉克铜镍锌合金"},"ambrain":{"p":"æm'breiin","t":"(=ambrein, ambrin)龙涎香脂, 龙涎精, 人造琥珀"},"ambraloy":{"w":"Ambraloy","p":"'æmbrәlɔi","t":"安布拉洛伊耐蚀铜合金"},"ambramycin":{"p":",æmbrә'maisin","t":"(=tetracycline)琥珀霉素,四环素"},"ambras":"(ambra 的复数) [医] 琥珀","ambre":"n. (Ambre)人名；(英、法)安布尔","ambrein":"[化] 龙涎香醇; 龙涎香精; 龙涎香素\\n[医] 龙涎香脂, 龙涎精","ambreinolide":"[化] 龙涎香内酯; 龙涎香精内酯","ambrette":{"p":"æm'bret","t":"(=musk seed)黄葵, 麝香梨"},"ambrettolide":{"p":"æm'bretә,laid","t":"黄葵内酯环十六烯, 麝香内脂"},"ambridge":{"w":"Ambridge","t":"n. (Ambridge)人名；(英)安布里奇"},"ambries":{"p":"'æmbrɪ","t":"n. 橱柜；教堂的圣器壁龛\\nn. (Ambry)人名；(法)安布里"},"ambrin":"[医] 龙涎香脂, 龙涎精","ambrine":{"p":"'æmbri:n","t":"安布林(成药, 用于烧伤及风湿性疾患)"},"ambrite":"[机] 新西兰产的一种沥青产品","ambriz":"[地名] [安哥拉] 安布里什","ambroid":{"p":"'æmbrɔid","t":"n. 合成琥珀"},"ambroin":{"p":"'æmbrɔin","t":"绝缘塑料, 合成琥珀, 假琥珀"},"ambrose":{"w":"Ambrose","p":"'æmbrәuz","t":"n. 安布罗斯(m.)"},"ambroses":{"p":"'æmbrəuz","t":"n. 安布罗斯（男子名）"},"ambrosia":{"p":"æm'brәuʒiә","t":"n. 仙果, 特别美味的食物\\n[医] 豕草属"},"ambrosiac":"n. 麝香气","ambrosiaceae":{"w":"Ambrosiaceae","t":"[网络] 豚草科；豕草科"},"ambrosial":{"p":"æm'brәuzjәl","t":"a. 特别美味的"},"ambrosially":{"p":"æm'brəuzjəli","t":"adv. ambrosial, ambrosian 的变形"},"ambrosian":{"p":"æm'brәjzjәn","t":"a. (=ambrosial)适用于神的, 美味的"},"ambrosin":{"p":"'æmbrәzin","t":"豕草素"},"ambrosine":{"p":"'æmbrәzi:n","t":"[矿]褐黄琥珀, 化石树脂"},"ambrosino":"[人名] 安布罗西诺","ambrosio":"n. (Ambrosio)人名；(西、英、意)安布罗西奥","ambrosius":"[人名] 安布罗修斯","ambrosterol":{"p":"æm'brɔstiәrɔl","t":"豕草甾醇, 豕草固醇"},"ambrotype":{"p":"'æmbrәtaip","t":"n. (采用玻璃底片的)旧式照相"},"ambroxol":"[化] 氨溴索","ambruticin":"安布鲁星","ambry":{"p":"'æmbri","t":"n. 橱柜, (教堂的)圣器壁龛"},"ambrym":"[地名] [瓦努阿图] 安布里姆岛","ambsace":{"p":"'eimzeis","t":"n. 最无价值的东西"},"ambu":{"p":"'æmbju:","t":"abbr. ambulance 救护车"},"ambucaine":"[化] 氨布卡因","ambucetamide":"[化] 氨布醋胺","ambulacra":{"p":",æmbju'lækrә","t":"柄吸盘, 吸垫, 步行足"},"ambulacral":{"p":"-krәl","t":"a. [动]步带的"},"ambulacralia":"步带板","ambulacrum":{"p":",æmbju'leikrәm","t":"n. [动]步带"},"ambulance":{"p":"'æmbjulәns","t":"n. 救护车\\n[医] 救护车"},"ambulanceman":{"p":"'æmbjʊlənsmæn","t":"n. 救护人员"},"ambulancemen":"n. （救护车, 船或飞机上的）救护人员( ambulanceman的复数形式 )","ambulances":{"p":"ˈæmbjulənsiz","t":"n. 救护车( ambulance的复数形式 )"},"ambulant":{"p":"'æmbjulәnt","t":"a. 走动的, 流动的\\n[医] 能走动的, 不卧床的"},"ambulante":{"p":",æmbju'lɑ:nt","t":"n. (法国18世纪用的)移动式茶几"},"ambulantes":"(ambulante 的复数) n. (法国18世纪用的)移动式茶几","ambulate":{"p":"'æmbjuleit","t":"vi. 移动, 步行, 走动"},"ambulated":{"p":"ˈæmbjuleitid","t":"v. 走动( ambulate的过去式和过去分词 )"},"ambulates":"v. 走动（ambulate的第三人称单数形式）","ambulating":{"p":"ˈæmbjuleitɪŋ","t":"v. 走动( ambulate的现在分词 )"},"ambulation":{"p":"æmbju'leiʃәn","t":"n. 移动, 步行"},"ambulator":{"p":"'æmbjuleitә","t":"(地测)测程轮, 测距计"},"ambulatorial":{"p":",æmbjulə'tɔ:riəl","t":"a. ＝ambulatory"},"ambulatories":{"p":"'æmbjʊlət(ə)rɪ","t":"a. 流动的；走动的；非固定的\\nn. [建] 回廊"},"ambulatorily":"adv. ambulatory的变形","ambulatorium":{"p":",æmbjulei'tɔriәm","t":"流动诊疗所, 门诊所"},"ambulators":"n. [测] 测距仪；测程轮","ambulatory":{"p":"'æmbjulәtәri","t":"a. 步行的, 走动的, 流动的, 非固定的\\nn. 回廊"},"ambulet":{"p":"'æmbjulit","t":"(长途)流动救护车"},"ambulette":{"p":"'æmbjulet","t":"n. (护送残疾人或老年人的)轻型救护车"},"ambulocetus":"陆行鲸","ambuphylline":"[化] 氨布茶碱","amburgos":{"p":"'æmbә:^әs","t":"[英]阿姆伯戈斯布(重浆白衬衫布)"},"ambury":{"p":"'æmbәri","t":"n. [兽医](牛马皮肤或粘膜上的)软瘤, [植]根茎肥大症"},"ambuscade":{"p":".æmbәs'keid","t":"n. 埋伏, 伏兵, 埋伏处\\nv. 打埋伏, 伏击"},"ambuscaded":{"p":"ˌæmbəsˈkeidid","t":"v. 埋伏, 伏击( ambuscade的过去式和过去分词 )"},"ambuscader":"n. 埋伏；伏兵 (ambuscade的变形)","ambuscades":"v. 埋伏, 伏击（ambuscade的第三人称单数形式）","ambuscading":{"p":"ˌæmbəsˈkeidɪŋ","t":"v. 埋伏, 伏击( ambuscade的现在分词 )"},"ambuscado":{"p":",æmbəs'keidəu","t":"n. [古语] = ambuscade"},"ambuscadoed":{"p":",æmbəs'keidəu","t":"n. [古语] = ambuscade"},"ambush":{"p":"'æmbuʃ","t":"n. 埋伏, 伏兵, 伏击\\nvt. 埋伏, 伏击\\nvi. 埋伏"},"ambushed":"a. 中埋伏的\\nv. 伏击（ambush的过去分词）；埋伏","ambusher":"n. 埋伏；机动侦查；伏击专家","ambushers":"(ambusher 的复数) n. 埋伏；机动侦查；伏击专家","ambushes":{"p":"ˈæmbʊʃiz","t":"n. 埋伏( ambush的名词复数 ); 伏击; 埋伏着的人; 设埋伏点\\nv. 埋伏( ambush的第三人称单数 ); 埋伏着"},"ambushing":{"p":"'æmbʊʃ","t":"n. 埋伏, 伏击；伏兵\\nvt. 埋伏, 伏击\\nvi. 埋伏"},"ambushment":"n. 埋伏, 伏击；伏兵 (ambush的变形)","ambuside":"[化] 安布赛特","ambustion":"[医] 灼伤","ambustoma":{"w":"Ambustoma","t":"[医] 美西螈属"},"ambutyrosin":{"p":"æm'bju:tәrәsin","t":"氨丁酰苷菌素"},"amby":"[地名] [澳大利亚] 安比","ambystoma":{"w":"Ambystoma","t":"钝口螈属"},"ambystomatidae":{"w":"Ambystomatidae","t":"钝口螈科"},"ambystomid":"[网络] 恶臭","ambystomoidea":{"w":"Ambystomoidea","t":"钝口螈亚目"},"amc":"abbr. 陆军装备司令部（Army Materiel Command）；航空与航天制造厂商委员会（Aerospace Manufactures Council）；自动信息计算（Automatic Message Counting）","amca":"abbr. Air Moving and Conditioning (Control) Association <美>空气流动与调节（控制）协会","amcbiasis":"阿米巴病","amchitka":{"w":"Amchitka","p":"æm'tʃitkə","t":"n. 安奇卡岛"},"amcide":{"w":"Amcide","p":"'æmsaid","t":"氨基磺酸铵"},"amcinafal":"安西法尔","amcinonide":"[化] 安西奈德","amco":"abbr. American Manufacturing Company 美国制造公司; American Oil Company 美国石油公司","amd":"abbr. 超微半导体公司（Advanced Micro Devices）","amda":"abbr. Airlines Medical Directors Association <美国>航空公司医务经理协会; Advanced for Mutual Defense Assistance 改进的相互防御援助; Advances for Mutual Defense Assistance 相互防御援助的改进; anti-malondialdehyde antibodies 抗丙二醛抗体","amdahl":{"w":"Amdahl","t":"[计] 阿姆德尔"},"amdam":"n. (Amdam)人名；(挪)阿姆丹","amdelate":"[医] 安德拉特(含杏仁酸铵的制剂)","amdinocillin":"[化] 阿姆地诺西林","amdro":"[化] 灭蚁腙","amds":{"w":"AMDS","t":"[计] 高级微机开发系统"},"amdt":"abbr. amendment 改善, 改正","amdur":"[人名] 阿姆杜尔","ame":{"w":"AME","t":"[计] 误差平均值"},"ameba":{"p":"ә'mi:bә","t":"n. 阿米巴, 变形虫\\n[医] 阿米巴, 变形虫"},"amebacidal":"[医] 杀阿米巴的","amebacide":{"p":"ә'mi:bәsaid","t":"杀阿米巴的, 杀阿米巴药"},"amebadiastase":"[医] 阿米巴淀粉酶","amebae":"pl. 阿米巴, 变形虫","amebaism":"[医] 阿米巴样运动力","ameban":{"p":"ə'mi:bən","t":"[医]卡巴胂：同carbarsone"},"amebaphobia":"[医] 阿米巴恐怖, 变形虫恐怖","amebas":"pl. 阿米巴, 变形虫","amebean":{"p":",æmə'bi:ən","t":"a. = amoebean"},"amebelodontinae":{"w":"Amebelodontinae","t":"美洲铲齿象亚科"},"amebiasis":{"p":",æmi'baiәsis","t":"n. [医]阿米巴病,变形虫病(尤指原虫寄生肠内引起的阿米巴痢疾)"},"amebic":{"p":"ә'mi:bik","t":"a. 阿米巴, 变形虫\\n[医] 阿米巴的, 变形虫的"},"amebicidal":"[医] 杀阿米巴的","amebicide":"[化] 抗阿米巴药\\n[医] 杀阿米巴的, 杀阿米巴药","amebid":"[医] 皮肤阿米巴疹","amebiform":"[医] 阿米巴样的, 变形虫样的","amebiosis":"[医] 阿米巴病, 变形虫病","amebism":"[医] 阿米巴样运动, 阿米巴病","amebocyte":{"p":"ә'mi:bәsait","t":"n. [医]阿米巴样细胞,变形细胞"},"amebocytogenous":"[医] 阿米巴样细胞产生的, 变形[虫样]细胞产生的","amebodiastase":"[医] 阿米巴淀粉酶","ameboid":{"p":"ә'mi:bɔid","t":"a. 阿米巴样的\\n[医] 阿米巴样的, 变形虫样的"},"ameboididity":"[医] 阿米巴样运动力","ameboidism":"[医] 阿米巴样运动","ameboma":"[医] 阿米巴瘤","amebosis":"阿米巴病","amebula":"[医] 变形虫样孢子, 假孢子虫","ameburia":"[医] 阿米巴尿, 变形虫尿","amec":"abbr. aft master-events controller 主要事件控制器","ameche":"[人名] 阿米奇","amed":"abbr. 中东对话（Asia-Middle East Dialogue）","ameda":"变形虫","amedalin":"氨甲达林","ameen":"n. (Ameen)人名；(阿拉伯、毛里求)阿明","ameer":{"p":"ә'miә","t":"n. 埃米尔(穆斯林国家酋长,王公,统帅的称号)"},"ameerate":{"p":"ә'miәrәt","t":"n. 穆斯林国家的身份或阶层"},"ameiosis":"[医] 不减数分裂","ameiuridae":{"w":"Ameiuridae","p":"ə'meijuraidi:","t":"n. 角鮠亚科；鮰科"},"ameiurus":{"w":"Ameiurus","t":"[网络] 鮰属；杜父鱼"},"amel":{"w":"AMEL","t":"[医] 航空医学设备实验室"},"amelanchier":"唐棣属","amelanotic":"[医] 无黑色素的","amelcorn":{"p":"'æməlkɔ:n","t":"n. 【植物】二粒小麦"},"ameleia":"[医] 无情感","amelia":{"p":"ә'mi:ljә","t":"[医] 无肢[畸形], 缺肢[畸形]"},"ameliaroside":"[化] 阿美糖苷","amelie":{"w":"Amelie","t":"n. 天使爱美丽（电影名）"},"amelification":{"p":"ә,mi:lifi'keiʃәn","t":"成釉(作用), 釉质化"},"ameling":"[人名] 阿梅林","amelio":"n. (Amelio)人名；(英)阿梅利奥；(法、葡)阿梅利奥","ameliorable":{"p":"ә'mi:ljәrәbl","t":"a. 可改善的"},"ameliorant":{"p":"ә'mi:ljәrәnt","t":"n. 改良物"},"ameliorate":{"p":"ә'mi:ljәreit","t":"v. 改善, 改良, 改进"},"ameliorated":{"p":"ə'miːlɪəreɪt","t":"vt. 改善；减轻（痛苦等）；改良\\nvi. 变得更好"},"ameliorates":{"p":"əˈmi:ljəˌreɪts","t":"n. <正, 夸>（使）改善, 改进( ameliorate的名词复数 )\\nv. <正, 夸>（使）改善, 改进( ameliorate的第三人称单数 )"},"ameliorating":{"p":"əˈmi:ljəˌreɪtɪŋ","t":"v. <正, 夸>（使）改善, 改进( ameliorate的现在分词 )"},"amelioration":{"p":"ә.mi:ljә'reiʃәn","t":"n. 改善, 改良, 改进\\n[医] 改善, 转佳"},"ameliorations":"(amelioration 的复数) n. 改善, 改良, 改进\\n[医] 改善, 转佳","ameliorative":{"p":"ә'mi:ljәrәtiv","t":"a. 起改善作用的"},"ameliorator":{"p":"ə'mi:ljəreitə","t":"n. 改良物；改良者"},"amelioratory":{"p":"ə'mi:ljərətiv;-təri","t":"a. 起改善(或改进、改良)作用的；起减轻(或缓和)作用的；【语言学】词义转佳的, 褒义的"},"ameliorer":"改善，改良，改进；修缮","ameloblast":{"p":"ә'melәblɑ:st","t":"n. (牙齿)成釉细胞"},"ameloblastic":{"p":"æmə'lɒblæstɪk","t":"[医]造釉的"},"ameloblastoma":{"p":",æmələu'blæstəmə","t":"n. [肿瘤] 成釉细胞瘤；[肿瘤] 造釉细胞瘤；[肿瘤] 釉母细胞瘤"},"ameloblastomas":{"p":",æmələu'blæstəmə","t":"【肿瘤学】成釉细胞瘤"},"amelodentinal":"[医] 釉牙[本]质的","amelogenesis":"[医] 釉质发生","amels":{"w":"Amels","t":"(AMEL 的第三人称 -s形式) [医] 航空医学设备实验室"},"ameluridae":{"w":"Ameluridae","t":"北美鲶科"},"amelus":"[医] 无肢畸胎, 缺肢畸胎","amemolite":{"p":"ә'mi:mәlait","t":"[地质]分支钟乳石"},"amen":{"p":".ɑ:'men","t":"interj. 阿门"},"amena":"n. (Amena)人名；(孟、捷)阿梅娜 (女名)， 阿梅纳","amenability":{"p":"ә.mi:nә'biliti","t":"n. 顺从, 义务"},"amenable":{"p":"ә'mi:nәbl","t":"a. 服从的, 会接纳的, 有义务的\\n[法] 服从的, 有责任的, 有服从义务的"},"amenableness":"[网络] 适应性","amenably":{"p":"ә'mi:nәbli","t":"adv. 顺从地, 服从地"},"amend":{"p":"ә'mend","t":"vt. 修改, 改善, 改良\\nvi. 改过自新"},"amendable":{"p":"ә'mendәbl","t":"a. 可修正的"},"amendatory":{"p":"ә'mendәtәri","t":"a. 起修正作用的, 改正的"},"amende":{"p":"æ'mә:nd","t":"n. 道歉, 赔偿"},"amended":"a. 修正的","amender":{"p":"ə'mendər","t":" 改正者, 修正者"},"amending":"[计] 修改","amendment":{"p":"ә'mendmәnt","t":"n. 修订, 改善, 改良, 改正\\n[化] 调理剂; 修正"},"amendments":{"p":"ə'mendmənts","t":"n. （法律、文件的）改动( amendment的复数形式 ); 修正案; 修改; （美国宪法的）修正案"},"amendola":"n. (Amendola)人名；(葡、意)阿门多拉","amends":{"p":"ә'mendz","t":"n. 赔偿\\n[经] 赔偿"},"amenhotep":{"w":"Amenhotep","p":",ɑ:mәn'hәutep","t":"阿孟和蒂(公元前十六至十四世纪 古埃及四法老中的任何一个)"},"amenia":"[医] 经闭","amenities":"n. 令人愉快之事物（amenity的复数）","amenity":{"p":"ә'mi:niti","t":"n. 便利设施, 适意, 礼仪\\n[法] 舒适, 方便, 优雅"},"ameno":"n. (Ameno)人名；(日)饴野(姓)","amenomania":"[医] 欣快狂","amenophis":{"w":"Amenophis","p":",æmә'nәjfis","t":"阿梅诺菲斯(即 Amenhotep)"},"amenorrhea":{"p":"ei,menә'ri:ә","t":"n. 经闭, 无月经\\n[医] 经闭, 无月经"},"amenorrheal":"[医] 经闭的, 无月经的","amenorrheic":" [医]无月经的, 闭经的, 停经的","amenorrhoea":"n. 经闭, 无月经","amenorrhoeal":"[网络] 闭经","amenorrhoeic":"[网络] 闭经","amens":{"p":"ɑː'men; eɪ-","t":"int. （表示衷心赞成）阿门；（祈祷时的结尾语）阿门\\nn. 祈祷的结束语；赞成\\nadv. 真实地\\nn. (Amen)人名；(法)阿芒；(英、罗、阿拉伯)阿门"},"amensalism":"[医] 无害寄生","ament":{"p":"'eimәnt","t":"n. 柔荑花序, 智力缺陷者\\n[医] 白痴"},"amenta":"n. 柔荑花序 (amentum的变形)","amentaceous":{"p":",æmәn'teiʃәs","t":"a. [植]葇荑花序的, 具葇荑花序的, 似葇荑花序的"},"amentia":{"p":"ә'menʃә","t":"n. 智力缺陷\\n[医] 智力缺陷, 精神发育不全, 精神错乱"},"amential":"[医] 智力缺陷的, 精神发育不全的, 精神错乱的","amentiferae":{"w":"Amentiferae","t":"[网络] 葇荑花序亚群；柔荑花序群；葇荑花序植物"},"amentiferous":{"p":",æmәn'tifәrәs","t":"a. 具葇荑花序的"},"amentiform":{"p":"ә'mentәfɔ:m","t":"[植]柔荑花序状的"},"amentoflavone":"[化] 阿曼托黄素; 8\"-双-4',5,7-三羟基黄酮","amentum":"[医] 柔荑花序","amer":"abbr. 美国的（等于American）；美国（等于America）；美国经济评论（American Economic Review）","amera":{"w":"Amera","t":"阿美动物部"},"amerasian":{"w":"Amerasian","p":"æmә'reiʃәn","t":"n. (尤指父亲是美国人,母亲是亚洲人的)美亚混血儿\\na. 美亚混血的"},"amerasians":{"p":",æmə'reiʒən; -reiʃən","t":"n. 美亚混血儿\\n美亚混血儿的"},"amerce":{"p":"ә'mә:s","t":"vt. 罚款, 罚钱, 惩罚\\n[法] 罚款, 罚金, 惩罚"},"amerceable":{"p":"ә'm\\\\\\\\:sәbl","t":"a. 可罚款的, 应罚款的"},"amerced":{"p":"ə'mɜːs","t":"vt. 罚款；惩罚"},"amercement":{"p":"'әm\\\\\\\\:smәnt","t":"n. 罚款, 罚金"},"amercements":"(amercement 的复数) n.罚款, 罚金","amercer":"n. amerce的变形","amerces":"v. 罚款, 惩罚（amerce的第三人称单数形式）","amerciable":{"p":"ә'mә:sәbl","t":"a. 应罚款的\\n[法] 应罚款的"},"amerciament":{"p":"'əmə:smənt; ə'mə:siəmənt","t":"n. 处罚；处以罚金, 课以罚款；任意罚款"},"amercing":{"p":"ə'mɜːs","t":"vt. 罚款；惩罚"},"amerenglish":{"w":"AmerEnglish","p":",æmәr'iŋ^liʃ","t":"n. 美国英语"},"ameri":"n. (Ameri)人名；(阿拉伯)阿米里","america":{"w":"America","p":"ә'merikә","t":"n. 美洲, 美国"},"americaine":"苯佐卡因","americal":"abbr. Americans in New Caledon ia (Army division) 新苏格兰的美国人（部队分部）","american":{"w":"American","p":"ә'merikәn","t":"n. 美国人\\na. 美国的, 美洲的"},"americana":{"p":"ә,meri'kɑ:nә","t":"n. 美国文物；美国文献"},"americaner":{"p":"əmerɪkən","t":"adj. 美洲的；(不计南极在内)西半球的\\nn. 美洲人，美洲公民；出生(或定居)于美洲的人；尤指；美洲印第安人"},"americanese":{"w":"Americanese","p":"ә'merikәni:z","t":"n. 美国英语"},"americanisation":{"p":"ə'merikəni'zeiʃən","t":"n. 美国化"},"americanisations":"(americanisation 的复数) n. 美国化","americanise":{"p":"əˈmerɪkənaɪz","t":"v. （使）美国化, （使）带上美国特点"},"americanised":"(americanise 的过去时) v. （使）美国化, （使）带上美国特点","americanising":"(americanise 的现在分词) v. （使）美国化, （使）带上美国特点","americanism":{"w":"Americanism","p":"ә'merikәnizәm","t":"n. 崇美主义, 美国英语的特点, 美国文化的特点"},"americanisms":{"w":"Americanisms","p":"ə'merikənizəm","t":"n. [美国英语]；美国(或美洲)特有的习俗(或风尚)；美国(或美洲)人的特性(或信仰)；美国(或美洲)文化的特点"},"americanist":{"w":"Americanist","p":"ә'merikәnist","t":"n. 研究美国问题的人, 亲美派"},"americanitis":{"p":"ә,merikә'naitis","t":"过度神经紧张"},"americanization":{"w":"Americanization","p":"ә,merikәnai'zeiʃən;-ni'z-","t":"n. 美国化"},"americanize":{"w":"Americanize","p":"ә'merikәnaiz","t":"vt. 使美国化"},"americanized":{"w":"Americanized","t":"a. 美国化的\\nv. 美国化（Americanize的过去分词）"},"americanizes":{"w":"Americanizes","p":"ə'merikənaiz","t":"vt., vi. [美国英语](在特性、方式、方法、理想等方面)(使)美国化；(使)与美国习俗(或用语等)同化；(使)带上美国特点"},"americanizing":{"p":"ə'merikənaiz","t":"vt. 使美国化\\nvi. 美国化"},"americanness":{"w":"Americanness","t":"n. 美国性"},"americano":{"p":"ɑ:,meri'kɑ:nəu","t":"n. 美式咖啡；美国佬；阿美利加诺（人名）"},"americanologist":{"w":"Americanologist","p":"ә,merikә'nɔlәdʒist","t":"n. 研究美国政府方针政策的专家"},"americanology":{"p":"ə,merikən'ɔlədʒi","t":"n. 美国问题研究，美国学"},"americanophobia":{"w":"Americanophobia","p":"ә,merikәnә'fәjbiә","t":"n. 对美国(或美洲)文化的憎恶,美国(或美洲)文化仇视心理"},"americanos":"n. 美式咖啡；美国佬；阿美利加诺（人名） (Americano的变形)","americans":{"w":"Americans","t":"n. 美国人（American的复数形式）"},"americas":{"w":"AMERICAS","p":"ə'merikəz","t":"n. 美洲"},"americate":"[化] 镅酸盐(或酯)","americium":{"p":".æmә'riʃiәm","t":"n. 镅\\n[化] 镅Am"},"americologue":{"w":"Americologue","p":"ә'merikәulɔ^","t":"n. 研究美国社会的学者"},"americom":" [计]= AMERIcan COMmunications,美国通信（技术，学）","americorps":"美国服务队（帮助社区建设、清洁和防止犯罪等，成员可领取报酬支付学费）","americus":"[人名] 阿梅里卡斯; [地名] [美国] 阿梅里克斯","americyl":{"p":"ә'merisil","t":"镅酰(离子), 双氧镅(离子)"},"amerigo":"n. 亚美利哥","amerika":{"w":"Amerika","p":"ә'merikә","t":"n. (纳粹)德国式亚美利加( 指美国社会法西斯主义或种族主义的一面)"},"amerikan":"adj. Amerika的变形","amerikaner":"adj. Amerika的变形","amerikas":{"p":"ə'merikə","t":"n. 德国式亚美利加（指美国社会法西斯主义或种族主义的一面）"},"amerind":{"w":"Amerind","p":"'æmәrind","t":"a. 美洲印第安人的"},"amerindian":{"w":"Amerindian","p":",æmә'rindjәn","t":"n. 美国印地安人或爱斯基摩人"},"amerindians":{"w":"Amerindians","t":"(Amerindian 的复数) n.美国印地安人或爱斯基摩人"},"amerindic":{"p":",æmər'indik","t":"a. 爱斯基摩人的; 美洲印第安人的"},"ameripol":{"p":"'æmәripɔl","t":"人造橡皮"},"amerisia":"[医] 说写不能","amerism":"[医] 不分节","ameristic":"[医] 不分节的","ameritech":"abbr. American Information Techno logies 美国信息技术","amerman":"n. (Amerman)人名；(英)阿默曼","ameroenglish":{"w":"AmeroEnglish","p":",æmerәj'iŋ^liʃ","t":"n. 美国英语"},"ameron":"亚美隆","amersfoort":{"w":"Amersfoort","p":"'ɑ:məs,fɔ:t","t":"n. 阿默斯福特（荷兰中部城市）"},"amersham":"[地名] [英国] 阿默舍姆","amerson":"n. (Amerson)人名；(英)阿默森","amertan":"[医] 阿默坦(用于烧伤的一种制剂)","amery":{"w":"Amery","t":"埃默里"},"ames":{"w":"AMES","p":"eimz","t":"[计] 自动信息输入系统"},"amesace":{"p":"'eimzeis","t":"n. 最无价值的东西"},"amesbury":"[地名] [加拿大、美国、英国] 埃姆斯伯里","amesdial":{"p":"ә'mesdjәl","t":"测微仪, 千分表"},"ameses":{"p":"eimz","t":"埃姆斯(美国艾奥瓦州城市)"},"amesiality":{"p":"eimi:zi'æliti","t":"不正中, 偏向一侧"},"amesite":{"p":"'eimzait","t":"镁绿泥石"},"ameslan":{"w":"Ameslan","p":"'æmәslæn","t":"n. 北美式手势语"},"amess":{"p":"eimz","t":"埃姆斯(美国艾奥瓦州城市)"},"ametabola":{"w":"Ametabola","t":"[医] 不变态类"},"ametabolic":{"p":",eimetә'bɔlik","t":"a. 不变形的"},"ametabolion":{"p":"ei,metә'bɔliɔn","t":"不变态类昆虫"},"ametabolism":{"p":"'eimә'tæbәlizәm","t":"无变态性"},"ametabolon":"[医] 不变态类","ametabolous":"[医] 不变态的","ametaboly":{"p":",eimә'tæbәli","t":"无变态的"},"ametachromiphil":{"p":"ei,metә'krәumәfil","t":"非偏染的, 正染色的"},"ametachromophil":"[医] 非偏染的, 正染色的","ametamorphosis":{"p":"ei,metә'mɔ:fәsis","t":"凝神多思症"},"ametaneutrophil":{"p":"ei,metә'nju:trәfil","t":"非偏染的, 正染色的"},"amethobottromycin":{"p":"ei,meθәu,bɔtrәu'maisin","t":"无甲基波卓霉素"},"amethocaine":{"p":"ә'meθәkein","t":"阿美索卡因, 丁卡因"},"amethone":"[医] 阿米同(用于平滑肌解痉的一种制剂商品名)","amethopterin":{"p":"ә,meθәup'terin","t":"n. [药]氨甲蝶呤"},"amethyst":{"p":"'æmiθist","t":"n. 紫水晶, 紫蓝色宝石\\n[化] 紫石英; 紫水晶; 紫晶"},"amethystine":{"p":",æmi'θistain","t":"a. 紫水晶质的, 紫色的"},"amethysts":{"p":"ˈæməθɪsts","t":"n. 紫蓝色宝石( amethyst的复数形式 ); 紫晶; 紫水晶; 紫色"},"amethystum":"紫水晶","ametoecious":{"p":"ә,mi:'ti:ʃәs","t":"n. (生态学用语)单主寄生的,不转主寄生的"},"ametria":"[医] 无子宫[畸形]","ametrohemia":"[医] 子宫血液缺乏","ametrometer":"[医] 屈光不正测量器, 变常眼测量器","ametrope":"[医] 屈光不正者","ametropia":{"p":",æmi'trәupiә","t":"n. 屈光异常, 非正视眼"},"ametropic":"[医] 屈光不正的, 变常眼的","ametrous":"[医] 无子宫的","ametryn":"[化] 莠灭净","amex":{"w":"Amex","p":"'æmeks","t":"n. 美国证券交易所"},"amey":"n. (Amey)人名；(法、西)阿梅；(英)埃米","amf":"abbr. 盟军机动部队（Allied Mobile Force）；认证管理功能（Authentication Management Function）","amfar":"abbr. American Foundation for AIDS Research 美国爱滋病研究基金会","amfebutamone":"安非布他酮","amfecloral":"安非氯醛","amfenac":"[化] 氨芬酸","amfepramone":"安非泼拉酮","amfetamine":"[化] 苯丙胺; 安非他明","amfetaminil":"安非他尼","amfetin":{"p":"'æmfetin","t":"阿姆费廷(一种组织兴奋药)"},"amfomycin":"[化] 安福霉素; 双霉素; 颖霉素","amfortas":{"w":"Amfortas","p":"ɑ:m'fɔ:tәs","t":"n. 安福塔斯(中世纪传奇中圣杯骑士的首领)"},"amg":"abbr. 自动磁性制导（Automatic Magnetic Guidance）","amga":{"w":"Amga","p":"'ɑ:mɡɑ:","t":"abbr. 美国登山向导协会（The American Mountain Guides Association）"},"amgen":"[医]阿目金（药厂名）","amgn":"abbr. Amgen Incorporated 阿姆坚有限公司","amgot":{"w":"Amgot","p":"'æm^ɔt","t":"n. ( 第二次世界大战盟军占领区的) 盟国军政府"},"amh":{"w":"Amh","t":"[医] 混合散光与主要近视"},"amhara":{"w":"Amhara","p":"ɑ:m'hɑ:rɑ:","t":"阿姆哈拉(埃塞俄比亚 一地区)"},"amharas":"n. 安哈拉人（埃塞俄比亚）","amharic":{"w":"Amharic","p":"æm'hærik","t":"n. 阿姆哈拉语"},"amherst":{"w":"Amherst","p":"'æmhә:st","t":"阿默斯特(姓氏)"},"amherstburg":"[地名] [加拿大] 阿默斯特堡","amherstite":"反纹二长岩","amhs":{"w":"AMHS","t":"[计] 自动信息处理系统"},"ami":{"p":"ɑ:'mi:","t":"abbr. 高级材料情报（Advanced Material Information）；美国食用肉类研究所（American Meat Institute）；航空英里指示器（Air Mileage Indicator）"},"amia":"n. (Amia)人名；(英)埃米娅\\n国际会计师公会颁发的联席会员证书（Affiliate Member of AIA）","amiability":{"p":"eimjә'biliti","t":"n. 和蔼可亲, 友善, 亲切"},"amiable":{"p":"'eimjәbl","t":"a. 亲切的, 和蔼可亲的\\n[法] 亲和的, 和蔼可亲的"},"amiableness":"n. 和蔼可亲","amiablility":{"p":"eimjәˊbiliti","t":"可爱,娇美"},"amiably":{"p":"'eimjәbli","t":"adv. 和蔼可亲地, 亲切地"},"amianite":{"w":"Amianite","t":"阿米奈特"},"amiant":{"p":"'æmjәnt","t":"石棉"},"amianth":"[化] 石麻(与石棉不同,纤维较长)","amianthine":{"p":",æmi'ænθin","t":"石棉, 石绒"},"amianthinopsy":{"p":",æmi,ænθi'nɔpsi","t":"蓝色盲"},"amianthoid":{"p":",æmi'ænθɔid","t":"石棉样的(指软骨坏变时所见某些纤维)"},"amianthosis":{"p":",æmiæn'θәusis","t":"石棉沉着病"},"amianthum":{"w":"Amianthum","t":"[网络] 杏仁"},"amianthus":{"p":",æmi'ænθәs","t":"n. 石棉的一种,石绒"},"amiantus":{"p":"æmiˊæntәs","t":"n. 一种石棉"},"amias":"埃米亚斯","amiben":"[化] 氨二氯苯酸铵盐; 草灭平铵盐","amic":{"p":"'æmik","t":"[医] 氨的"},"amica":"abbr. Automobile Mutual Insurance Company of America 美国汽车相互保险公司","amicability":{"p":".æmikә'biliti","t":"n. 友善, 温和"},"amicable":{"p":"'æmikәbl","t":"a. 友善的, 友好的\\n[法] 友好的, 和睦的, 温和的"},"amicableness":"n. amicable的变形","amicably":{"p":"'æmikәbli","t":"adv. 友善地"},"amicarbalide":"[化] 双脒苯脲","amice":{"p":"'æmis","t":"n. (神职人员的)白麻布披巾, 带头兜的披肩"},"amicetamine":"[医] 友霉糖醚","amicetin":{"p":",æmi'si:tin","t":"(=allomycin)友霉素, 别霉素"},"amichai":"n. (Amichai)人名；(以)阿米凯","amici":{"w":"Amici","t":"阿米西"},"amicia":"[人名] 阿米西娅","amicibone":"[化] 阿米西酮","amicinafide":"安西非特","amicine":{"p":"æ'maisin","t":"(垂体后叶)生长抑制素"},"amick":{"w":"Amick","t":"阿米克尼龙丝"},"amiclenomycin":{"p":",æmiklinәu'maisin","t":"氨基丁酸霉素"},"amico":"abbr. 美国测量仪器公司（american measuring instrument company）","amicrobic":{"p":",eimai'krәubik","t":"无菌的, 非微生物性的, 无微生物的"},"amicron":{"p":"ei'mai,krɔn","t":"n. [化]次微(胶)粒,超微子"},"amicrone":"[医] 超视粒, 绝微子","amicronucleate":{"p":"ei,maikrәu'nju:kliit","t":"缺乏微核的"},"amicroscopic":{"p":"ei,maikrә'skɔpik","t":"超显微镜的"},"amictic":"非需精的","amiculum":"[医] 小脑齿状核包膜","amicus":{"p":"æ'mɪkəs","t":"n. 法官的顾问"},"amicuscuriae":{"p":"әˊmaikәsˊkjuәriiː","t":"n. 法院的顾问"},"amicycline":"阿米环素","amid":{"p":"ә'mid","t":"prep. 在其间, 在其中\\n[经] 在...中"},"amida":{"p":"'ɑ:mi:dɑ:","t":"n. 阿弥陀佛"},"amidable":{"p":"'æmidәbl","t":"[机] 可酰氨化的"},"amidah":{"p":"a'mi:dɑ:","t":"n. 犹太教的一种礼拜仪式"},"amidalgon":"吗苯丁酯","amidantel":"阿米登太","amidase":{"p":"'æmideis","t":"n. [生化]酰胺酶"},"amidate":{"p":"'æmideit","t":"v. [化]化为醯胺"},"amidated":"(amidate 的过去时) v.[化]化为醯胺","amidating":"[建] 酰氨化的, 酰氨化(作用)","amidation":"[化] 酰胺化; 酰胺化作用","amide":{"p":"'æmaid","t":"n. 氨化物, 酰胺\\n[化] 酰胺"},"amidephrine":"[化] 阿米福林","amides":{"p":"æ'maɪdz","t":" [医]酰胺（类）, 氨化物"},"amidin":{"p":"'æmidin","t":"n. [化]粉溶素"},"amidinase":"[医] 脒基酶, 脱脒基酶","amidine":{"p":"'æmi,di:n","t":"n. [化]脒"},"amidines":"(amidine 的第三人称 -s形式) n.[化]脒","amidinomycin":"[化] 脒霉素","amidinothiourea":"[化] 脒硫脲","amidinourea":"[化] 脒脲","amido":{"p":"ә'mi:dәu","t":"n. 氨基\\na. 氨基的"},"amidobenzene":{"p":",æmidә'benzi:n","t":"苯胺, 阿尼林"},"amidocephalin":{"p":",æmidә'sefәlin","t":"氨基脑磷脂"},"amidogen":{"p":"ә'midәdʒәn","t":"n. (=amido)[化]氨基"},"amidogroup":{"p":"ә'mi:dәj^ru:p","t":"n. [化](氨化物中的)(酰)胺基"},"amidohexose":{"p":",æmidә'heksәus","t":"氨基己糖"},"amidohpdrolase":"[机] 酰氨水解","amidohydrolase":{"p":",æmidәj'haidrәleis","t":"n. [生化]酰胺水解酶"},"amidol":{"p":"'æmidɒl","t":"n. 阿米酚\\n[化] 阿米酚; 阿米多; 二氢氯化-2,4-二氨基苯酚"},"amidolysis":{"p":",æmi'dәulisis","t":"酰胺分解"},"amidomethylation":{"p":",æmidәu,meθ'leiʃәn","t":"酰胺甲基化作用"},"amidomycin":{"p":",æmidәu'maisin","t":"(=myxoviromycin)胺霉素, 粘病毒霉素"},"amidomyelin":{"p":",æmidә'maiәlin","t":"氨基髓磷脂"},"amidon":"[化] 美沙酮","amidone":{"p":"'æmidәun","t":"n. 〈药〉美沙酮（镇静剂）"},"amidonitrogen":"[化] 酰胺态氮","amidophen":"[医] 阿米多芬(内含氨基吡啶、乙酰非那替汀、咖啡因和莨菪浸膏)","amidopurine":{"p":",æmidә'pjuәri:n","t":"腺嘌呤, 氨基嘌呤"},"amidopyrin":"[机] 氨基","amidopyrine":{"p":"ә,mi:dәu'pairi:n","t":"[药]氨基比林, 匹拉米洞"},"amidosulphate":{"p":"ә,mi:dәu'sʌlfeit","t":"氨基磺酸盐(酯)"},"amidoxalyl":"[化] 氨基草酰","amidoxime":"[化] 偕胺肟\\n[医] 氨肟","amidoxyl":"[化] 羟氨基\\n[医] 羟氨基","amidpulver":{"p":"'æmid'pʌlvә","t":"酰胺粉, 硝铵, 硝酸钾, 炭末炸药"},"amidrazone":"[化] 氨基腙; 氨基某腙","amids":"Advanced Multispectral Image Descriptor System 高级多光谱图像描述器系统；Area Manpower Instructional Development System 地区人力指导开发系统","amidship":{"p":"ә'midsʃip","t":"adv. 在船中部, 向船的中部"},"amidships":{"p":"ә'midʃips","t":"adv. 在船体中部\\n[机] 船体中央部"},"amidst":{"p":"ә'midst","t":"prep. 在...当中"},"amidulin":{"p":",æmi'du:lin","t":"可溶性淀粉"},"amie":{"p":"ɑ:'mi:","t":"n. （法）女朋友"},"amiel":"n. (Amiel)人名；(西、法)阿米耶尔；(德、以)阿米尔；(英)埃米尔","amiens":{"w":"Amiens","p":"'æmiәnz","t":"亚眠[法国北部城市]"},"amies":"[英格兰人姓氏] 埃米斯 Amis的变体","amiet":"[人名] 埃米特","amiga":"n. 女性朋友；一种多媒体计算机的商标","amigen":"[医] 阿米根(一种蛋白质水解物的商品名)","amigin":"安眠静","amigo":{"p":"ә'mi:gәu","t":"n. 朋友"},"amigos":{"p":"ә'mi:ɡәuz","t":"n. 朋友（amigo的复数形式）"},"amiidae":{"w":"Amiidae","t":"弓鳍科"},"amiiformes":{"w":"Amiiformes","t":"弓鳍目"},"amik":"n. 阿米克; 1976年加拿大蒙特利尔夏季奥运会吉祥物; 吉祥物已经成为奥运会的传统; 被选为吉祥物的动物是海狸","amikacin":{"p":"ә'mikәsin","t":"氨基羟丁基卡那霉素A(即：抗菌素BBK8)"},"amikhellin":"阿米凯林","amil":{"p":"'ɑ:mil","t":"(=aumil)[史](印度)收税员, 税款包收员"},"amilan":{"w":"Amilan","p":"'æmilәn","t":"聚酰胺(树脂, 纤维)"},"amilcar":"n. (Amilcar)人名；(西、罗、葡)阿米尔卡","amilomer":"阿米洛姆","amilon":{"w":"Amilon","t":"阿米隆聚酯纤维"},"amiloride":"[化] 阿米洛利","amimia":"[医] 表情不能, 无表情, 拟态缺失","amimycin":"[化] 竹桃霉素\\n[医] 夹竹桃霉素","amin":"n. 阿敏（七十年代乌乾达的独裁者）","amina":"n. (Amina)人名；(哈萨、乌兹、吉尔、塔吉、坦桑、孟、阿拉伯)阿明娜 (女名), 阿米纳","aminable":"[机] 可氨化的","aminacrine":"[化] 氨吖啶; 氨基吖啶\\n[医] 氨基吖啶","aminah":"n. (Aminah)人名；(印尼)阿米娜","aminal":"[化] 缩醛胺","aminarsone":"[医] 卡巴胂, 对脲基苯胂酸","aminase":"[医] 脱氨基酶","aminata":"n. (Aminata)人名；(几、塞内)阿米纳塔","aminate":{"p":"'æmineit","t":"v. 氨化"},"aminated":"胺化了的","aminating":"[机] 氨化的, 氨化(作用)","amination":"[化] 氨基化; 胺化; 胺化作用(直接加入氨基)","aminazin":{"p":"ә'minәzin","t":"n. [药]氯丙嗪(源自苏联商标名)"},"aminazine":"[医] 阿米那金, 氯丙嗪","amindan":"磺胺磺柳酸","amine":{"p":"ә'mi:n","t":"n. 胺, 卤氮化合物\\n[化] 胺"},"amineptine":"[化] 阿米庚酸","amines":"[医]胺","aminet":{"p":"'æminet","t":"阿米内特(含氨茶硷和戊巴比妥钠)"},"aminex":{"w":"Aminex","p":"'æmineks","t":"多孔性阴离子交换树脂"},"aming":{"p":"em","t":"abbr. 调幅\\nv. 是\\nn. (Am)人名；(柬)安"},"amini":"n. (Amini)人名；(法、捷、伊朗)阿米尼","aminic":{"p":"ə'mi:nik","t":"a. amine的变形；【有机化学】胺的"},"aminiform":"胱胺","aminimide":"[化] 胺化酰亚胺","aminitrozole":"[化] 醋胺硝唑","amino":{"p":"'æminәu","t":"a. 氨基的\\n[医] 氨基"},"aminoacetal":"[化] 氨基乙缩醛","aminoacethydrazide":"[机] 氨基乙酰胼","aminoacetone":{"p":",æminәu'æsitәun","t":"[机] 氨基丙酮, 丙酮基氨"},"aminoacetonitrile":"[化] 氨基乙腈","aminoacetophenetidine":"[医] 氨乙酰基非那替汀, 非诺可","aminoacetophenone":"[化] 氨基苯乙酮\\n[医] 氨基乙酰苯, n-氨基苯乙酮","aminoacid":{"p":"æmɪ'nəʊsɪd","t":"氨"},"aminoacidopathy":"氨基酸病","aminoacids":"(aminoacid 的复数)  氨","aminoaciduria":{"p":"ә'minәuæsi'djuәriә","t":"n. [医]氨基酸尿(症)"},"aminoacyl":"[化] 氨酰基","aminoacylhydrazine":"[化] 氨酰肼","aminoadipaldehyde":"[化] 氨基己二酸半醛","aminoaldehexose":"[化] 氨基己醛糖","aminoalizarin":"[机] 氨基茜素","aminoalkane":"[网络] 氨基烷烃","aminoanisole":{"p":",æminәu'ænisәul","t":"氨基茴香醚, 氨基苯甲醚"},"aminoazabenzol":"氨基偶氮苯","aminoazobenzene":"[机] 氨基偶氮苯","aminobenzaldehyde":"[机] 氨基苯(甲)醛","aminobenzaldoxime":"[化] 氨基苯醛肟; 氨基苯甲醛肟","aminobenzene":{"p":"ә,mi:nәu'benzi:n","t":"n. [化]氨基苯, 酸"},"aminobenzenesulfonamide":{"p":"ә,mi:nɔ,benzi:sʌl'fɔnәmaid","t":"磺胺, 氨苯磺胺"},"aminobenzidine":"[机] 氨基联苯氨","aminobenzine":"[网络] 氨基苯","aminobenzoic":"a. 氨基苯甲[酸]","aminobenzonitrile":"[化] 氨基苄腈","aminobenzophenone":"[化] 氨基二苯酮; 氨基二苯甲酮","aminobenzothiazole":"[化] 氨基苯并噻唑","aminobenzylation":"[化] 氨苄基化; 氨苄基化作用","aminobiphenyl":"[化] 苯基苯胺; 氨基联苯","aminobphenyl":"氨基联苯","aminocaine":"[医] 氨基卡因(戊氨基乙基对氨基苯甲酸酯)","aminocarb":{"p":",æminәukɑ:b","t":"灭害威(杀虫剂)"},"aminocellulose":{"p":",æminәu'seljulәus","t":"氨基纤维素"},"aminochlorthenoxazin":"[化] 氨氯苯┭嗪","aminocidin":"氨基杀菌素","aminocyclitol":"氨基环醇","aminodeoxykanamycin":{"p":"'æminәu,di:ɔksi,kɑ:nә'maisin","t":"卡那霉素B"},"aminodimethylbenzene":"[化] 二甲苯胺","aminodiphenylamine":"[机] 氨基二苯氨","aminodiphenylmethane":"[机] 氨基二苯甲烷","aminoethane":"[化] 乙胺; 氨基乙烷","aminoethanol":"氨基乙醇","aminoethylacetanilide":"[化] 乙酰氨苯基乙胺","aminoethylbenzene":"[机] 氨基乙苯","aminoethylcellulose":{"p":",æminәu,eθil'seljulәus","t":"氨乙基纤维素"},"aminoffite":{"p":"'æminәfait","t":"铍密黄石"},"aminoform":{"p":"'æminәu,fɔ:m","t":"氨仿, 环六亚甲基四胺, 乌洛托品"},"aminogalactose":{"p":",æminәu'^ælәktәus","t":"氨基半乳糖, 半乳糖胺"},"aminogenesis":{"p":",æminәu'dʒenisis","t":"氨基的形成, 生氨作用"},"aminoglucose":{"p":",æminәu'^lu:kәus","t":"氨基葡萄糖, 葡糖胺"},"aminoglutethimide":"[化] 氨鲁米特","aminoglutethimidium":"氨基导眠能","aminoglycoside":{"p":",æminə'ɡlikəsaid","t":"n. 氨基糖苷类"},"aminoglycosides":"(aminoglycoside 的复数) n. 氨基糖苷类","aminoguanidine":"[化] 氨基胍\\n[医] 氨基胍","aminohexane":"[化] 氨基己烷; 己胺","aminohexose":"[化] 氨基己糖","aminohydrolase":{"p":",æminәu'haidrәleis","t":"氨基水解酶"},"aminoids":{"p":"'æminɔidz","t":"氨米诺德(主要含氨基酸及二肽物, 营养剂)"},"aminoil":"abbr. American Independent Oil Company 美国独立石油公司","aminoketone":{"p":",æminәu'ki:tәun","t":"氨基酮, [pl. ] 氨基酮类"},"aminoketones":"氨基酮类","aminokrovin":{"p":",æminәu'krәuvin","t":"蛋白质水解物"},"aminolipid":{"p":",æminәu'lipid","t":"氨基脂, 氨脂质"},"aminolipin":"[医] 氨基脂","aminolysis":{"p":",æmi'nɔlisis","t":"氨解(作用), 成氨分解"},"aminomercuration":"[化] 氨汞化","aminomethanamidine":"[医] 胍","aminomethane":{"p":",æminәu'meθein","t":"氨基甲烷"},"aminomethyl":{"p":",æminәu'meθil","t":"氨甲基"},"aminomethylation":{"p":",æminәu,meθi'leiʃәn","t":"氨甲基化作用或过程"},"aminometradine":{"p":",æminә'metrәdi:n","t":"氨尿嘧啶, 6-氨基-3-乙-2-烯丙基尿嘧啶"},"aminomycetin":"[化] 氨基菌素","aminomycin":{"p":",æminәu'maisin","t":"(=fungimycin)氨基霉素,真菌霉素"},"aminomycinum":"[医] 氨基霉素","aminomyelin":"[医] 氨基髓磷脂","aminonialyase":{"p":",æmin'nɔniә,leis","t":"解氨酶"},"aminonucleoside":"[医] 氨基核甙","aminooxamide":"[化] 氨基草酰肼","aminopentamide":"[化] 胺戊酰胺","aminopentane":"[机] 氨基戊烷","aminopeptidase":{"p":"ә,minә'peptideis","t":"n. [生化]氨基肽酶"},"aminopeptodrate":"[医] 水解蛋白, 卡米诺伊德","aminophenazone":"氨基比林","aminophenol":{"p":"ә,mi:nәu'fi:nәul","t":"[机] 氨基酚"},"aminophenylacetonitrile":"[化] 氨基苯乙腈","aminophenylglycine":"[化] N-氨基苯乙氨酸","aminophenylsulfone":"[医] 氨苯砜","aminopherase":{"p":",æmә'nɔfәreis","t":"氨基转氨酶, 转氨霉"},"aminophylline":{"p":"әmi:nәu'fili:n","t":"n. [药]氨茶碱"},"aminoplast":{"p":"ә'mi:nәuplɑ:st","t":"n. [化]氨基塑料"},"aminoplastice":"[机] 氨基塑料","aminoplastics":"[化] 氨基塑料","aminopolypeptidase":"[化] 氨基多肽酶\\n[医] 氨基多肽酶","aminopolypetidase":{"p":"ә,mi:nәupɔli'peptideis","t":"氨基多肽酶, 氨基多胜酵素"},"aminopromazine":"[化] 氨丙嗪","aminopropanol":"氨丙醇","aminopropionitrile":"[化] 氨基丙腈","aminopropylbenzene":"[机] 氨基丙苯","aminopropylon":"[化] 氨丙吡酮","aminoprotease":{"p":"ә,mi:nәu'prәutieis","t":"氨基蛋白酶"},"aminopterin":{"p":",æmi'nɔptәrin","t":"n. [药]氨喋呤"},"aminopurine":{"p":",æminә'pju:rin","t":"氨基嘌呤"},"aminopyridine":{"p":"ә,minәu'piridi:n","t":"氨基吡啶"},"aminopyrine":{"p":"ә'mi:nәu'pairi:n","t":"n. 一种无色透明化合物,氨基比林"},"aminoquin":"[医] 氨基喹(扑疟喹啉的一种)","aminoquinaldines":"[医] 氨基喹哪啶类(2-甲基喹啉的氨基衍生物,用于杀锥虫)","aminoquincarbamide":"[化] 双氨甲喹脲","aminoquinol":"[化] 阿米诺喹","aminoquinoxaline":"[化] 氨基喹喔啉","aminoresorcinol":"[机] 氨基间苯二酚","aminorex":"[化] 阿米雷司","aminos":"氨基酸过多","aminosaccharide":{"p":",æminәu'sækәraid","t":"氨基糖"},"aminosal":{"p":"ә'mi:nәu,sæl","t":"水解蛋白(质)"},"aminosalicylate":{"p":"æmɪnəʊzə'lɪsɪleɪt","t":"[医]氨基水杨酸盐"},"aminosalicylates":"(aminosalicylate 的复数)  [医]氨基水杨酸盐","aminosidin":"巴龙霉素","aminosidine":{"p":",æmi'nɔsidi:n","t":"(=paromoycin)氨苷菌素, 巴龙霉素"},"aminosin":{"p":"ә'mi:nә,sin","t":"2-丙烯基硫脲, 烯丙硫脲"},"aminosis":"[医] 氨基酸过多[症]","aminosol":{"p":"ә'mi:nәu,sɔl","t":"血纤维蛋白水解产物"},"aminostiburea":"[医] 脲锑胺甙","aminosugar":{"p":",æminәu'ʃu^ә","t":"氨基糖"},"aminosuria":"[医] 胺尿","aminothiazole":{"p":"ә,mi:nәu'θiәzәul","t":"氨基噻唑"},"aminothiouracil":"[医] 氨基硫脲嘧啶","aminothiourea":{"p":",æminәu'θaiәu,juәriә","t":"氨基硫脲"},"aminotoluene":"[医] 氨基甲苯","aminotransferase":{"p":"ә,mi:nәu'trænsfә,reis","t":"n. 氨基转移酶, 转氨酶"},"aminotransferases":"(aminotransferase 的复数) n. 氨基转移酶, 转氨酶","aminotransferation":"转氨作用; 氨基移作用","aminotriazloe":"[机] 氨基三唑","aminotriazole":{"p":"ә,mi:nәu'traiә,zәul","t":"n. [化]氨基三唑(一种除草剂)"},"aminoxylene":"[化] 二甲苯胺","aminoxytriphene":"胺氧曲芬","aminozide":"[化] 二甲基琥珀酰肼; 丁二酸一酰(2,2-二甲基)肼","amins":"abbr. 最小声幅","aminta":"n. (Aminta)人名；(英)阿明塔","aminu":"n. (Aminu)人名；(尼日利)阿米努","aminuria":"[医] 胺尿","amioca":"[化] 支链淀粉","amiodarone":"[化] 胺碘酮","amiosis":"[医] 不减数分裂","amiot":"[人名] 阿米奥特","amiphenazole":"[化] 阿米苯唑\\n[医] 氨苯唑","amiphos":{"w":"Amiphos","t":"敌磷杀虫剂"},"amir":{"p":"ә'miә","t":"n. 埃米尔(穆斯林国家的酋长等称号)"},"amira":"n. (Amira)人名；(阿拉伯、法、罗)阿米拉","amiran":"n. (Amiran)人名；(俄、格鲁)阿米兰","amirate":{"p":"ә'mireit","t":"(=ameerate)酋长国"},"amire":"automatic diagnostic maintenance information retrieval 自动诊断维护信息检索","amiri":"n. (Amiri)人名；(阿拉伯、法、哈萨、乌兹、吉尔、塔吉)阿米里；(日)网利(姓)","amirs":"(amir 的复数) n. 埃米尔(穆斯林国家的酋长等称号)","amis":{"w":"AMIS","p":"'eimis","t":"[计] 采集管理信息系统, 先进管理信息系统, 自动化管理信息系统"},"amish":{"p":"'ɑ:miʃ","t":"n. 孟诺教派；孟诺教派之教徒"},"amisometradine":"[化] 阿米美啶","amiss":{"p":"ә'mis","t":"a. 有毛病的, 出差错的\\nadv. 错误地, 不顺当, 有缺陷地"},"amisses":"(amiss 的复数) a. 有毛病的, 出差错的\\nadv. 错误地, 不顺当, 有缺陷地","amissing":"(amiss 的现在分词) a. 有毛病的, 出差错的\\nadv. 错误地, 不顺当, 有缺陷地","amistad":"n. （西）友谊","amit":"n. 阿米特（男子名）","amita":"n. (Amita)人名；(日)网田(姓)","amitabha":{"w":"Amitabha","p":".ʌmi'tɑ:bә","t":"n. 阿弥陀佛"},"amitai":"n. (Amitai)人名；(以)阿米塔伊","amital":{"p":"'æmitæl","t":"阿米他, 异戊基, 乙基巴比土酸"},"amite":"[地名] [美国] 阿米特","amiterol":"阿米特罗","amithiozone":"[医] 硫醋腙","amities":{"p":"'æmɪtɪ","t":"n. 友好；亲善关系；友好关系\\nn. (Amity)人名；(英、中非)阿米蒂"},"amiton":"[化] 胺吸磷","amitosis":{"p":".æmi'tәusi:s","t":"n. 无丝分裂, 直接分裂\\n[医] 无丝分裂, 直接分裂"},"amitotic":"[医] 无丝分裂的","amitotically":{"p":",æmi'tɔtikəli","t":"adv. amitosis的变形"},"amitraz":"[化] 阿米曲士(食欲增进药); 虫螨脒","amitriptyline":{"p":",æmi'triptli:n","t":"n. 阿米替林(抗抑郁药)\\n[化] 阿米替林"},"amitriptylinoxide":"[化] 氧阿米替林","amitrol":{"p":"'æmitrɔl","t":"n. 氨基三唑,杀草强(一种除草剂)"},"amitrole":{"p":"'æmitrɔ:l","t":"n. 氨基三唑,杀草强(一种除草剂)"},"amity":{"p":"'æmiti","t":"n. 友好, 亲善关系"},"amityville":"[地名] [美国] 阿米蒂维尔","amixetrine":"[化] 阿米西群; 阿米特林","amixia":"[医] 交配不能","amizol":"[化] 杀草强; 氨二唑","amjad":"n. (Amjad)人名；(阿拉伯、孟、巴基)阿姆贾德","aml":{"w":"AML","t":"[计] 先进数学库, 应用模块库, 阵列机语言, 汇编微程序库"},"amlcd":"有源矩阵液晶显示器（active matrix liquid crystal display）","amli":"n. (Amli)人名；(阿拉伯)阿姆莱","amlin":"[人名] 阿姆林","amm":"n. (Amm)人名；(阿拉伯)阿姆\\nabbr. 反导弹导弹（Anti-Missile Missle）；飞机维护手册（Aircraft Maintenance Manual）；亚太经合组织部长级会议（APEC MinisteriaI Meeting）","amma":{"p":"'ʌmɑ:","t":"[医][=American-Mexican Medical Association]美国-墨西哥医学协会"},"amman":{"w":"Amman","p":"æ'mɑ:n","t":"n. 安曼(约旦首都)"},"ammanian":{"w":"Ammanian","p":"'æmәniәn","t":"[地质]安曼阶"},"ammann":"n. (Ammann)人名；(德、法)阿曼；(英)安曼","ammar":"n. (Ammar)人名；(法、葡、阿拉伯、英)阿马尔","ammargenum":"[医] 氨化硝酸银液, 氨银液","ammate":{"w":"Ammate","p":"'æmeit","t":"氨基磺酸铵"},"amme":"n. (Amme)人名；(德)阿梅","ammelide":"[化] 三聚氰酸一酰胺; 氰尿酰胺; 里尿酸","ammeline":"[化] 三聚氰酸二酰胺; 氰尿二酰胺","ammen":{"p":"æ'mɑ:n","t":"n. 安曼"},"ammer":"n. 阿默尔（姓氏）","ammerman":"[人名] 安默曼","ammersoaite":{"p":"æ'mә:sә,ait","t":"钙伊利石"},"ammersooite":"阿米水云母","ammesia":"健忘症","ammeter":{"p":"'æmitә","t":"n. 安培计\\n[化] 安培计"},"ammeters":"(ammeter 的复数) n. 安培计\\n[化] 安培计","ammi":{"w":"Ammi","t":"[医] 阿密属"},"ammikhellin":"[医] 阿密基林","ammine":{"p":"'æmi:n","t":"n. [化]氨络物"},"ammines":{"p":"'æmiːn","t":"n. 氨络物；氨合物"},"ammino":{"p":"'æminәu","t":"[机] 氨络"},"amminopolypeptidase":"[机] 氨基多","ammiol":"阿米醇","ammiolite":{"p":"'æmiә,lait","t":"锑铵汞矿(辰砂与锑酸酮的混合物)"},"ammirati":"[人名] 阿米拉蒂","ammism":"[医] 沙浴疗法","ammo":{"p":"'æmәu","t":"n. 军火, 弹药"},"ammobium":"[网络] 银苞菊","ammochthad":{"p":"æ'mәutʃθæd","t":"沙岸植物"},"ammocoete":"幼七鳃鳗","ammocolous":{"p":",æmә'kɔ:lәs","t":"a. [生]砂生的,栖砂的"},"ammodiscacea":{"w":"Ammodiscacea","t":"沙盘虫总科"},"ammodyte":{"p":"'æmə,dait","t":"n. 【植物学】砂生植物"},"ammodytes":{"w":"Ammodytes","p":"'æmə,dait","t":"n. 【植物学】砂生植物"},"ammodytidae":{"w":"Ammodytidae","t":"[网络] 玉筋鱼科"},"ammodytoidei":{"w":"Ammodytoidei","t":"玉筋鱼亚目"},"ammoket":{"w":"Ammoket","t":"[医] 安莫克特(一种杏仁酸铵的ю剂)"},"ammon":{"w":"Ammon","p":"'æmәn","t":"n. (古埃及的)阿蒙神"},"ammonal":{"p":"'æmәnæl","t":"n. 阿芒拿尔炸药\\n[化] 阿芒拿(硝铵、铝、炭)炸药"},"ammonate":"[化] 氨合物; 氨络物","ammonation":{"p":",æmә'neiʃәn","t":"氨合作用"},"ammonemia":"[医] 氨血[症]","ammonfication":"成氨作用","ammongelatine":"[机] 铵胶, 阿芒吉力","ammonia":{"p":"ә'mәunjә","t":"n. 氨水, 阿摩尼亚\\n[化] 氨"},"ammoniac":{"p":"ә'mәuniæk","t":"a. 氨的, 含氨的\\nn. 氨草胶"},"ammoniacal":{"p":"ә'mәuniækәl","t":"a. [化]氨的, 氨性的"},"ammoniacum":"[化] 氨草胶\\n[医] 阿摩匿, 阿摩尼亚脂","ammonialyase":{"p":",әmәuniә'laieis","t":"解氨酶"},"ammoniameter":"[医] 氨量计, 氨浓度计","ammonianmeter":"[机] 氨量计","ammoniate":{"p":"ә'mәunieit","t":"n. [化]氨化合物\\nv. 以氨处理, 加氨"},"ammoniated":{"p":"ә'mәunieitid","t":"a. 充氨的, 含氨的\\n[化] 充氨的; 含氨的"},"ammoniates":"v. 以氨处理, 加氨( ammoniate的第三人称单数 )","ammoniating":"[化] 充氨的; 充氨; 充氨作用","ammoniation":{"p":"ә,mәjni'әiʃən","t":"n. [化]含氨化合物"},"ammonic":{"p":"ә'mәunik","t":"a. [化]氨的,铵的"},"ammoniemia":"[医] 氨血[症]","ammonification":{"p":"ә,mәunifi'keiʃәn","t":"n. [化]加氨(作用), 氨化(作用)"},"ammonified":"v. 加氨于, 使氨化( ammonify的过去式和过去分词 )","ammonifier":{"p":"ә'mәuni,faiә","t":"氨化细菌"},"ammonifiers":{"p":"ә'mɔnifaiәz","t":"[复] n.[微]氨化菌"},"ammonifies":"v. 加氨于, 使氨化( ammonify的第三人称单数 )","ammonify":{"p":"ә'mәunifai","t":"v. [化]加氨于, 使氨化"},"ammonifying":"[机] 生氨, 加氨","ammoninted":"[医] 加氨的, 含氨的","ammonio":"氨溶的","ammonioborite":{"p":"ә'mәuniәu'bɔ:rait","t":"水铵硼石"},"ammonioformaldehyde":"[医] 甲醛氨, 环六亚甲基四铵, 乌洛托品","ammoniogen":{"p":"ә'mәuniәu,dʒәn","t":"生氨剂"},"ammoniogenesis":{"p":"ә,mәuniәu'dʒenisis","t":"生氨作用"},"ammoniojarosite":"铵黄铁矾; 铵黄铁钾矾","ammoniometer":{"p":"ә,mәuni'ɔmitә","t":"[机] 氨量计"},"ammonionitrometry":"[医] 氨氮测定法","ammonirrhea":"[医] 氨排泄","ammonistion":"氨化","ammonite":{"p":"'æmәnait","t":"n. 菊石\\n[化] 菊石; 干肉粉; 阿芒炸药; 硝铵二硝基萘炸药"},"ammonites":"(ammonite 的复数) n. 菊石\\n[化] 菊石; 干肉粉; 阿芒炸药; 硝铵二硝基萘炸药","ammonitic":{"p":",æmə'nitik","t":"a. 【古生物学】菊石型的, 菊石式"},"ammoniticone":{"p":",æmә'naitә,kәun","t":"菊石壳"},"ammonium":{"p":"ә'mәunjәm","t":"n. 铵\\n[化] 铵"},"ammoniuria":{"p":"ә,mәuni'juәriә","t":"氨尿(症)"},"ammonization":"[化] 氨化作用","ammonlbacteria":"氨细菌类","ammono":{"p":"'æmәnәu","t":"氨的, 含氨的"},"ammonobase":{"p":"æ'mәunәu,beis","t":"氨基金属"},"ammonoid":{"p":"'æmә,nɔid","t":"n. 菊石(已灭绝的头足动物)"},"ammonoidea":{"w":"Ammonoidea","t":"菊石亚纲; 菊石亚纲"},"ammonoids":"(ammonoid 的复数) n.菊石(已灭绝的头足动物)","ammonol":{"p":"'æmәnɔl","t":"安莫诺(苯乙酰胺、苯胺与迄盐制剂止痛药)"},"ammonolysis":{"p":"æmә'nɔlisis","t":"n. [化]氨解作用"},"ammonolyze":{"p":"'æmәunәlaiz","t":"氨解"},"ammonotelic":{"p":",æmәunә'telik","t":"a. [动]排泄氨的(指淡水鱼、 蛙等排出氨为主要氮废物)"},"ammonotelism":{"p":",æmә'nɔtelizm","t":"n. [动]排氨代谢"},"ammonpulver":{"p":",æmәn'pʌlvә","t":"[机] 铵炸药"},"ammons":"n. (Ammons)人名；(英)安蒙斯","ammophos":"[化] 安福粉(一种磷酸铵肥料)","ammophoska":"[化] 安福钾","ammoresinol":"阿摩树脂醇","ammotelism":"[机] 排铵代谢","ammotherapy":{"p":",æmә'θerәpi","t":"沙浴疗法"},"ammotragus":{"w":"Ammotragus","t":"[网络] 鬣羊属；蛮羊属；髯羊"},"ammoxidation":{"p":"æ,mɔksi'deiʃәn","t":"(=oxidative ammonolysis)氨氧化反应(作用), 氨解氧化(作用)"},"ammunition":{"p":".æmju'niʃәn","t":"n. 军火, 弹药\\n[机] 弹药"},"ammunitioned":{"p":"æmjʊ'nɪʃ(ə)n","t":"n. 弹药, 军火；[比喻]炮弹(可用来为自己辩护或攻击别人的依据、证据、材料等), 进攻(或防御)手段\\nvt.,vi. 装弹药(于)；供弹药(给)"},"ammunitioning":{"p":"æmjʊ'nɪʃ(ə)n","t":"n. 弹药, 军火；[比喻]炮弹(可用来为自己辩护或攻击别人的依据、证据、材料等), 进攻(或防御)手段\\nvt.,vi. 装弹药(于)；供弹药(给)"},"ammunitions":"(ammunition 的复数) n. 军火, 弹药\\n[机] 弹药","ammuntion":"军火","amn":{"w":"Amn","t":"n. 飞行员\\nn. (Amn)人名；(英)阿门"},"amna":"n. (Amna)人名；(厄立)阿姆纳","amnemonic":"[医] 记忆障碍的","amnesia":{"p":"æm'ni:zjә","t":"n. 健忘症, 记忆缺失\\n[医] 记忆缺失, 遗忘[症]"},"amnesiac":{"p":"æm'ni:zi,æk","t":"[医] 遗忘者"},"amnesiacs":"(amnesiac 的复数) [医] 遗忘者","amnesias":"(amnesia 的复数) n. 健忘症, 记忆缺失\\n[医] 记忆缺失, 遗忘[症]","amnesic":{"p":"æm'ni:zik","t":"a. 记忆缺失, 健忘(症)\\n[医] 遗忘的"},"amnesics":"(amnesic 的复数) a. 记忆缺失, 健忘(症)\\n[医] 遗忘的","amnestic":{"p":"æm'nestik","t":"a. 记忆缺失, 健忘(症)\\n[医] 遗忘的, 引起遗忘的"},"amnestied":{"p":"'æmnɪstɪ","t":"n. 大赦, 特赦\\nvt. 对…实行大赦"},"amnesties":{"p":"ˈæmnɪsti:z","t":"n. 大赦( amnesty的名词复数 )"},"amnestrogen":{"p":"æm'nestrәdʒәn","t":"混雌激素(由雌激素或其水溶共轭物所组成的混合物)"},"amnesty":{"p":"'æmnisti","t":"n. 大赦, 赦免"},"amnestying":{"p":"'æmnɪstɪ","t":"n. 大赦, 特赦\\nvt. 对…实行大赦"},"amnh":"[医][=American Museum of natural history]美国自然史博物馆","amnia":"[医] 羊膜","amnic":"[网络] 野蛮人","amnicolous":{"p":"'æmnikәlәs","t":"a. [生]栖沙滩的"},"amnio":{"p":"'æmniəu","t":"abbr. 羊膜穿刺术（amniocentesis）"},"amniocentesis":{"p":".æmniәusen'ti:sis","t":"n. 羊膜穿刺术"},"amniochorial":"[医] 羊膜绒[毛]膜的","amnioclepsis":"[医] 羊水溢","amnioembryonic":"[医] 羊膜胚的","amniogenesis":"[医] 羊膜形成","amniography":{"p":",æmni'ɔ^rәfi","t":"n. [医]羊水造影术,羊水照相术"},"amnioma":"[医] 羊膜瘤","amnion":{"p":"'æmniәn","t":"n. 羊膜\\n[医] 羊膜"},"amniongenesis":"羊膜形成","amnionic":{"p":",æmni'ɔnik","t":"a. [动][解]羊膜的,有羊膜的"},"amnionitis":"[医] 羊膜炎","amnions":"羊膜, <口>胞衣( amnion的名词复数 )","amnioplastin":"[医] 干羊膜(成药,用于颅骨切开术后防止粘连)","amniorrhea":"[医] 羊水溢","amniorrhexis":"[医] 羊膜破裂","amnios":{"p":"'æmniəu","t":"abbr. 羊膜穿刺术（amniocentesis）"},"amnioscope":"羊膜镜","amnioscopy":{"p":",æmni'ɔskәpi","t":"n. [医]羊水镜检法"},"amniosis":"[医] 羊膜炎","amniota":{"w":"Amniota","t":"[医] 羊膜动物类"},"amniote":"[医] 羊膜动物","amniotes":" [医]羊膜类, 羊膜动物","amniotic":"a. 羊膜的\\n[医] 羊膜的","amniotin":"[医] 安尼奥廷(含雌性激素物质的油剂,用如雌酮)","amniotitis":"[医] 羊膜炎","amniotome":"[医] 羊膜穿破器","amniotomy":"[医] 羊膜穿破术","amnitis":"[医] 羊膜炎","amnon":"n. (Amnon)人名；(以)阿姆农","amo":"abbr. 美国眼力健公司（Advanced Medical Optics）；编程对象模型（Analysis Management Object）","amobam":{"w":"Amobam","t":"代森铵"},"amobarbita":"安密妥","amobarbital":{"p":",æmәu'bɑ:bitɔ:l","t":"n. 异戊巴比妥"},"amoben":{"w":"Amoben","t":"草灭平"},"amoco":{"w":"Amoco","t":"abbr. 美国石油公司（American Oil Company）"},"amodeo":"n. (Amodeo)人名；(西、法)阿莫德奥","amodiaquin":{"p":",æmәu'daiәkwin","t":"n. [药]氨酚喹(抗疟药)"},"amodiaquine":"[化] 阿莫地喹\\n[医] 阿莫待喹, 卡莫喹","amodin":"安曲菌素","amodrine":"[医] 阿莫德林(一种抗支气管痉挛和镇静剂)","amodyn":{"w":"Amodyn","p":"'æmәudin","t":"阿莫丁炸药"},"amoeba":{"p":"ә'mi:bә","t":"n. 阿米巴, 变形虫\\n[医] 阿米巴属, 变形虫属"},"amoebacide":"[化] 杀变形虫剂\\n[医] 杀阿米巴的, 杀阿米巴药","amoebae":{"p":"ә'mi:bi:","t":"pl. 阿米巴, 变形虫"},"amoeban":{"p":"ә'mi:bәn","t":"a. 阿米巴的, 阿米巴性的"},"amoebas":{"p":"ə'miːbə","t":"n. 阿米巴；变形虫（单细胞生物）"},"amoebean":{"p":"æmi'bi:әn","t":"a. 对答体的"},"amoebiasis":{"p":",æmi'baiәsis","t":"n. [医]阿米巴病,变形虫病(尤指原虫寄生肠内引起的阿米巴痢疾)"},"amoebic":{"p":"ә'mi:bik","t":"a. 变形虫的, 变形虫状的"},"amoebida":{"w":"Amoebida","p":"ə'mi:bidə","t":"n. 变形目；阿米巴目"},"amoebidae":{"w":"Amoebidae","t":"[医] 阿米巴科, 变形科"},"amoebiform":{"p":"ə'mi:bəfɔ:m","t":"a. = amoeboid"},"amoebina":{"w":"Amoebina","t":"[医] 阿米巴目, 变形目"},"amoebiosis":"[网络] 变形虫症","amoebobacter":{"w":"Amoebobacter","t":"[医] 阿米巴细菌属"},"amoebobacterieae":{"w":"Amoebobacterieae","t":"[医] 阿米巴样细菌族"},"amoebocyte":{"p":"ә'mi:bәsait","t":"n. [医]阿米巴样细胞,变形细胞"},"amoeboid":{"p":"ә'mi:bɒid","t":"a. 似变形虫的"},"amoebotaenia":{"w":"Amoebotaenia","t":"[医] 变形带[绦虫]属"},"amoebous":"[网络] 变形虫","amoebula":"[医] 小阿米巴","amoeda":"变形虫","amogastrin":"阿莫胃泌素","amoi":"n. 夏新（品牌名称）","amoil":"[化] 酞酸戊酯","amok":{"p":"ә'mɔk","t":"adv. 乱砍乱杀, 杀气腾腾地横冲直撞\\n[医] [抑郁后暴发]杀人狂"},"amol":{"p":"ə'mɒl","t":"abbr. acute monocytic leukemia 急性单核细胞性白血病"},"amolanone":"[化] 阿莫拉酮","amole":{"p":"ә'mәulei","t":"n. 皂用植物"},"amoment":"n. 片刻","amomum":"豆蔻属\\n砂仁","amon":{"p":"'ɑ:mәn","t":"文件实时监控"},"among":{"p":"ә'mʌŋ","t":"prep. 在...之中"},"amongst":{"p":"ә'mʌŋst","t":"prep. 在...当中, 在...之间, 在...之中"},"amontillado":{"p":"ә.mɒnti'lɑ:dou","t":"n. 白葡萄酒"},"amoproxan":"[化] 克冠吗啉","amor":{"p":"'eimɔ","t":"[医] 恋爱, 爱情"},"amora":{"p":"ɑ:'məurɑ:","t":"n. 阿莫拉（犹太教律法学者，犹太教口传律法集《塔木德》的编集者）"},"amoral":{"p":"ei'mɒrәl","t":"a. 不属于道德范畴的, 无从区分是非的"},"amoralia":"[医] 悖德痴愚","amoralis":"[医] 悖德痴愚者","amoralism":{"p":"eɪ'mɒrəlɪzəm","t":"非道德论"},"amoralist":"n. amoral的变形","amorality":{"p":".eimɔ'rælәti","t":"n. 超道德, 非道德；道德无涉性"},"amorally":"adv. amoral的变形","amorce":{"p":"ә'mɒ:s","t":"n. 玩具手枪的雷管, 点火药"},"amore":"n. 爱茉莉（韩国化妆品公司）；爱慕（歌曲名）","amores":"n. (Amores)人名；(西、葡)阿莫雷斯","amoret":{"p":"'æməret","t":"n. 相思结, 同心结；爱慕的一瞥；秋波"},"amoretti":"小爱神( amoretto的名词复数 )","amoretto":{"p":"'ɑ:mә'retәu","t":"n. 小爱神"},"amorim":"n. (Amorim)人名；(西、葡)阿莫里姆","amorism":{"p":"'æmәrizəm","t":"n. 谈情说爱"},"amorist":{"p":"'æmәrist","t":"n. 谈情说爱者, 言情小说作者"},"amoristic":{"p":",æmə'ristik","t":"a. amorist的变形"},"amorite":{"w":"AMorite","p":"'æmәrait","t":"n. 亚摩利人(语)"},"amorites":{"w":"Amorites","t":"(AMorite 的复数) n.亚摩利人(语)"},"amorosa":"[电影]阿莫罗萨","amorosity":{"p":",æmə'rɔsəti","t":"n. amorous的变形"},"amoroso":{"p":",æmә'rәjsәj","t":"n. 葡萄醇香酒"},"amorous":{"p":"'æmәrәs","t":"a. 多情的, 表示爱情的, 恋爱的"},"amorously":{"p":"'æmərəsli","t":"adv. 好色地；妖艳地"},"amorousness":"n. amorous的变形","amorph":"无效基因","amorpha":"[医] 无定形[病], 擦烂","amorphia":"[医] 无定形[现象], 非晶形[现象]","amorphic":{"p":"ə'mɔ:fik","t":"adj. 无定形的；无条理的"},"amorphin":"[化] 紫穗槐苷","amorphinism":{"p":"ә'mɔ:fә,nizәm","t":"吗啡瘾(状态)"},"amorphism":{"p":"ә'mɒ:fizm","t":"n. 无定形, 非晶形, 不结晶性\\n[化] 非晶形; 非晶形现象"},"amorphization":{"p":"ə,mɔ:fi'zeiʃən","t":"n. 无定形化"},"amorphognosia":{"p":"ei,mɔ:fә^'nәusiә","t":"形态失认"},"amorphophallus":"魔芋属","amorphous":{"p":"ә'mɒ:fәs","t":"a. 无定形的, 无组织的\\n[化] 非晶形的; 无定形的"},"amorphously":"无定形地（amorphous的变体）; 无一定方向（或目的）地（amorphous的变体）","amorphousness":"n. 无定形态；非晶形态","amorphus":"[医] 无定形畸胎","amors":{"p":"'eimɔ:","t":"n. （拉）埃莫（爱神丘比特，等于Cupid）"},"amort":{"p":"ә'mɔ:t","t":"a. 无生气的, 意志消沉的, 濒于死亡的"},"amorth":"n. (Amorth)人名；(意)阿莫尔特","amortisable":"a. amortise的变形","amortisation":{"p":"ә,mɔ:tai'zeiʃən;-ti'z-","t":"n. 分期偿还, 摊还"},"amortise":{"p":"ә'mɔ:taiz,'æmә-","t":"v. 摊还"},"amortised":"(amortise 的过去分词) v.摊还","amortisement":"n. 摊还, 分期偿还","amortises":"(amortise 的第三人称 -s形式) v.摊还","amortising":"(amortise 的现在分词) v.摊还","amortisseur":"阻尼器","amortizable":"可分批偿还的","amortizatin":"摊提","amortization":{"p":"ә,mɔ:ti'zeiʃәn","t":"[计] 分期付款\\n[化] 缓冲作用"},"amortize":{"p":"ә'mɒ:taiz","t":"vt. 摊还, 摊销, 分期偿还\\n[法] 把不动产让与, 转让, 分期偿还"},"amortized":{"p":"'əmɔ:taɪzd","t":"v. <商>分期偿还（债务）( amortize的过去式和过去分词 )"},"amortizement":{"p":"ә'mɔ:tizmәnt, ,æmә'taiz-","t":"n. 摊还"},"amortizes":{"p":"ˈæməˌtaɪziz","t":"v. <商>分期偿还（债务）( amortize的第三人称单数 )"},"amortizing":{"p":"ˈæməˌtaɪzɪŋ","t":"v. <商>分期偿还（债务）( amortize的现在分词 )"},"amory":{"w":"Amory","p":"'eiməri","t":"n. 艾默利（姓氏）"},"amos":{"w":"Amos","p":"'eimәs","t":"n. 阿摩司(<<圣经>>人物)"},"amosan":"阿膜散","amoscanate":"[化] 硝硫氰胺; 异硫氰酸胺苯酯","amosite":"[化] 铁石棉(填充剂)","amoss":{"p":"'eimɔs","t":"n. 阿莫斯，艾莫斯(男子名)；【圣经】"},"amotion":{"p":"ə'məuʃən","t":"[古语]；(对雇员的)撤换"},"amotivational":{"p":",eimәjti'veiʃənәl","t":"a. 缺乏动机"},"amotriphene":"[化] 胺氧三苯","amott":"n. (Amott)人名；(英、葡)阿莫特","amou":"[地名] [法国] 阿穆","amount":{"p":"ә'maunt","t":"n. 总数, 总额\\nvi. 总计, 等同"},"amounted":{"p":"ə'maʊnt","t":"vi. 总计, 合计；相当于；共计；产生…结果\\nn. 数量；总额, 总数"},"amounting":{"p":"ə'maʊnt","t":"vi. 总计, 合计；相当于；共计；产生…结果\\nn. 数量；总额, 总数"},"amounts":"n. 数量, 总额（amount的复数）","amour":{"p":"ә'muә","t":"n. 偷情, 性爱\\n[法] 奸情, 不正当的男女关系, 恋爱"},"amoureux":"n. (Amoureux)人名；(法)阿穆勒","amours":{"p":"əˈmuəz","t":"n. 奸情, 恋情( amour的复数形式 )"},"amove":{"p":"ə'mu:v","t":"vt. 【法律】开除；把…免职；辞退；把…强行遣送"},"amoxapine":"[化] 阿莫沙平","amoxecaine":"[化] 阿莫卡因","amoxiciliin":"阿摩西林","amoxicillin":"[化] 阿莫西林; 羟氨苄青霉素","amoxil":"阿莫西林","amoxin":"[医] 阿莫克辛(一种治痛风药)","amoxy":{"p":"æ'mɔksi","t":"[机] 戊氧基"},"amoxycillin":{"p":"ә,mɔksә'silin","t":"n. [药]羟氨苄青霉素"},"amoy":{"p":"ә'mɔi","t":"n. 厦门（中国城市）"},"amozonolysis":{"p":"'ә,mәuzәu'nɔlisis","t":"氨(解)臭氧化反应[作用]"},"amp":{"p":"æmp","t":"n. 安培\\n[化] 腺苷酸; 腺苷一磷酸"},"ampacity":{"p":"æm'pæsiti","t":"[电] 安培容量"},"ampakine":"安帕金（药物）","ampalaya":"胶苦瓜","ampangabeite":{"p":",ɑ:mpɑ:n'^ɑ:bi,ait","t":"钶钛铁铀矿, 铌钇矿"},"amparo":"n. (Amparo)人名；(西、葡)安帕罗","ampas":"abbr. 奥斯卡学院，电影艺术与科学学院（Academy of Motion Picture Arts and Sciences）","ampasimenite":{"p":",æmpә'siminait","t":"霓霞斑岩"},"ampco":"铝铁青铜","ampcoloy":{"w":"Ampcoloy","t":"耐蚀耐热铜合金"},"ampe":"abbr. automated message processing exchange 自动化信息[报文]处理交换机","amped":"a. 激动的; 兴奋的","ampeliscidae":{"w":"Ampeliscidae","t":"藤钩虾科"},"ampelite":{"p":"'æmpә,lait","t":"黄铁炭质页岩, 硫铁黑土"},"ampelopsin":"[化] 白蔹素\\n[医] 蛇葡萄素, 白蔹素","ampelopsis":{"p":".æmpi'lɒpsis","t":"n. 蛇葡萄\\n[医] 蛇葡萄属, 白蔹属"},"ampelotherapy":{"p":",æmpәlәu'θerәpi","t":"葡萄疗法"},"amperage":{"p":"'æmpәridʒ","t":"n. 安培数\\n[医] 安培度"},"ampere":{"p":"'æmpєә","t":"n. 安培\\n[化] 安培"},"amperehour":{"p":"ˊæmpєәrˊauә","t":"n. 安培小时"},"amperemeter":"n. 电流计, 安培计\\n[化] 安培计","amperemeter,amperometer":"[化] 安培计; 电流计","amperes":{"p":"ˈæmˌpɪəz","t":"n. <电>安培( ampere的复数形式 )"},"amperite":{"p":"'æmpeәrait","t":"n. 镇流管, 限流器\\n[电] 限流器"},"amperomeier":"[机] 安培计, 电流表","amperometer":"n. 安培计","amperometric":{"p":"æmpi:rә'metrik","t":"a. [物]安培计的, 电流计的"},"amperometry":{"p":",æmpi:'rɔmitri","t":"电流分析, 电流测定法"},"amperozide":"[化] 安哌齐特","ampersand":{"p":"'æmpәsænd","t":"[计] \"&\"号"},"ampersands":"(ampersand 的复数) [计] \"&\"号","ampes":"(ampe 的复数) abbr. automated message processing exchange 自动化信息[报文]处理交换机","ampetometry":"[化] 电流分析; 电流分析法","ampex":"n. 安派克斯录像机；安培（美国公司）","amphalius":{"w":"Amphalius","t":"[医] 双形蚤属"},"amphamphoterodiplopia":"[医] 两眼复视","ampharetidae":{"w":"Ampharetidae","t":"双栉虫科"},"ampharetinae":{"w":"Ampharetinae","t":"双栉虫亚科"},"amphauxesis":"[医] 同心性增生","ampheclexis":"[医] 两性选择","amphecloral":"[化] 胺苯氯醛","amphedroxyn":"[医] 脱氧麻黄硷(商品名)","amphemera":"[医] 每日热","amphemerous":"[医] 日发的, 每日的","amphenidone":"[化] 安非尼酮","amphenone":"氨苯丁酮","ampherotokous":"[医] 单体两性生殖的","ampherotoky":{"p":",æmfә'rɔtәki","t":"(=amphitoky)单体两性生殖"},"amphetamine":{"p":"æm'fetәmi:n","t":"n. 苯丙胺, 安非他明\\n[化] 苯丙胺; 苯异丙胺; 安非他民; 1-苯基-2-丙胺"},"amphetamines":{"p":"æm'fetəmi:nz","t":"n. 安非他明( amphetamine的复数形式 )"},"amphetaminil":"[化] 苯丙胺苄氰","amphiapomict":{"p":",æmfi'æpәmikt","t":"有性无性生殖个体, 双性无融合生殖植物"},"amphiarkyochrome":"[医] [双]网染细胞","amphiarthrodial":"[医] 微动关节的","amphiarthrosis":{"p":",æmfiɑ:'θrәusis","t":"n. 丛和关节"},"amphiaster":{"p":"'æmfiæstә","t":"n. 双星体, 双星型"},"amphibia":{"p":"æm'fibiә","t":"n. 两栖类\\n[医] 两栖类"},"amphibian":{"p":"æm'fibiәn","t":"a. 两栖类的, 水陆两用的\\nn. 两栖动物, 水旱两生植物, 水陆两用飞机"},"amphibians":{"p":"æm'fɪbɪənz","t":"n. 两栖动物( amphibian的复数形式 ); 水陆两用车; 水旱两生植物; 水陆两用飞行器"},"amphibioidei":{"w":"Amphibioidei","t":"双生绦虫科"},"amphibiology":{"p":"æm,fibi'ɔlәdʒi","t":"n. 两栖动物学"},"amphibiotic":{"p":",æmfibai'ɔtik","t":"a. [动]幼时生长于水中,长大生活在陆地的"},"amphibious":{"p":"æm'fibiәs","t":"a. 水陆两栖的, 能两栖作战的, 陆海空军协同作战的\\n[医] 两栖的"},"amphibiously":"adv. amphibious的变形","amphibiousness":"n. amphibious的变形","amphibioustroops":{"p":"æmˊfibiәstruːps","t":"n. 两栖部队"},"amphiblastic":"[医] 两极囊胚的","amphiblastula":"[医] 两极囊胚","amphiblestritis":"[医] 视网膜炎","amphiblestrodes":"[医] 视网膜","amphiblestroid":"[医] 网状的, 视网膜的","amphibole":{"p":"'æmfibәul","t":"n. 闪石\\n[化] 角闪石"},"amphiboles":"(amphibole 的复数) n. 闪石\\n[化] 角闪石","amphibolia":{"p":",æmfi'bәuliә","t":"动摇期, 不稳定期"},"amphibolic":{"p":",æmfi'bɔlik","t":"a. [矿]闪石的,语意含混的"},"amphibolidae":{"w":"Amphibolidae","t":"网纹螺科"},"amphibolide":"闪石岩","amphibolies":{"p":"æm'fɪbəlɪ","t":"n. 模棱两可；意义含糊"},"amphibolips":{"w":"Amphibolips","t":"[网络] 两栖动物"},"amphibolite":{"p":"æm'fibәlait","t":"[机] 闪岩"},"amphibolization":"闪石化; 闪岩化","amphibological":{"p":"æm,fibə'lɔdʒikəl","t":"a. amphibology的变形"},"amphibologies":{"p":",æmfɪ'bɒlədʒɪ","t":"n. 暧昧的词句；意义含混的词句"},"amphibology":{"p":".æmfi'bɒlәdʒi","t":"n. 语言模棱两可, 意义含混的词句"},"amphibolous":{"p":"æm'fibәlәs","t":"a. 模棱两可\\n[医] 动摇的, 不稳定的, 预后未定的"},"amphiboly":{"p":"æm'fibәli","t":"n. 模棱两可的言辞, 暧昧的词句"},"amphibrach":{"p":"'æmfibræk","t":"n. [语]短长短格"},"amphicar":{"p":"'æmfikɑ:","t":"n. 水陆两用车"},"amphicarcinogenic":"[医] 两向性生癌的","amphicarpaea":{"w":"Amphicarpaea","t":"[网络] 两型豆属；野毛扁豆属；野扁毛豆"},"amphicarpic":{"p":",æmfi'kɑ:pik;-pəs","t":"a. 【植物学】；两季成熟的"},"amphicarpous":{"p":",æmfi'kɑ:pәs","t":"具两种果实的"},"amphicarpy":{"p":",æmfi'kɑ:pi","t":"地上下结果性"},"amphicelous":"[医] 两[边]凹的","amphicentric":{"p":",æmfi'sentrik","t":"起止同源的(血管)"},"amphichelydia":{"w":"Amphichelydia","t":"两栖龟亚目"},"amphichiralty":"[化] 兼手性","amphichroic":{"p":",æmfi'krәuik","t":"a. [化]双变色的,两性反应的"},"amphichromatic":"[化] 两变色的\\n[医] 双变色的, 两性反应的","amphichromation":"两性反应的","amphichrome":{"p":",æmfi'krәumi","t":"双色植物, 两色花"},"amphicoela":{"w":"Amphicoela","t":"两凹亚目"},"amphicoelian":{"p":",æmfi'si:liәn","t":"a. [动](鱼的脊椎骨等)两凹的"},"amphicoelous":{"p":",æmfi'si:lәs","t":"a. [动]两端或两面皆凹的\\na. [动](鱼的脊椎骨等)两凹的"},"amphicrania":{"p":",æmfi'kreiniә","t":"n. [医]两侧头痛"},"amphicreatine":"[医] 两性肌酸","amphicreatinine":"[医] 两性肌酸酐","amphicribral":"週韧的","amphicroic":"[医] 双变色的, 两性反应的","amphicryptophyte":"两栖植物","amphictyon":{"p":"æm'fiktiәn","t":"n. 近邻各邦联盟"},"amphictyonic":{"p":"æm,fikti'ɔnik","t":"a. 近邻同盟的"},"amphictyonies":{"p":"æm'fɪktɪənɪ","t":"近邻同盟"},"amphictyons":"n. 近邻同盟（amphictyon的复数）","amphictyony":{"p":"æm'fiktiәni","t":"n. 近邻同盟"},"amphicyonidae":{"w":"Amphicyonidae","t":"半狗科"},"amphicyte":"[医] 套细胞","amphicytula":"[医] 受精卵, 受精端黄卵","amphid":"[医] 头感器","amphidesmic":"[医] 两接的","amphidesmous":"两韧带的","amphidetic":{"p":",æmfi'detik","t":"两面伸展的, 全韧带"},"amphidiarthrosis":{"p":",æmfi,daiә'θrәusis","t":"屈戌动关节"},"amphidiploid":{"p":",æmfi'diplɔid","t":"a. & n.[生]双二倍体(的)"},"amphidiploidy":{"p":"æmfɪdɪp'lɔɪdɪ","t":"双二倍性"},"amphidisc":"[医] 两极胚盘","amphidiscophora":{"w":"Amphidiscophora","t":"两盘亚纲"},"amphidiscosa":{"w":"Amphidiscosa","t":"两盘目"},"amphierotism":{"p":",æmfi'erәtizm","t":"两性色情"},"amphigamous":{"p":",æm'fi^әmәs","t":"a. [生]无性器官的"},"amphigamy":{"p":",æmfi'^æmi","t":"受精作用"},"amphigastrium":"腹叶","amphigastrula":"[医] 两极原肠胚","amphigean":{"p":"'æmfədʒi:n","t":"n. 【生态学】(美洲与欧亚非大陆的)共有生物[亦作 amphigeic ]"},"amphigene":{"p":"'æmfə,dʒi:n","t":"n. [矿物] 白榴石"},"amphigenesis":{"p":",æmfi'dʒenisis","t":"有性生殖, 两性生殖"},"amphigenetic":{"p":",æmfidʒi'netik","t":"有性生殖的, 两性生殖的"},"amphigenous":{"p":"æm'fidʒənəs","t":"a. 【微生物学】两面生的, 遍生的"},"amphigonadism":"两性生殖腺共存","amphigonium":"[医] 两性生殖期(疟原虫在蚊体内)","amphigony":{"p":"æm'fi^әni","t":"两性生殖, 有性生殖"},"amphigoric":{"p":",æmfi'ɡɔ:rik","t":"a. amphigory, amphigouri的变形"},"amphigory":{"p":"'æmfi^әri","t":"n. 无意义而滑稽的文章"},"amphigouri":"n. 无意义而滑稽的文章","amphigynous":{"p":"æm'fidʒәnәs","t":"两面生的"},"amphihaploid":{"p":"æm'fihæplɔid","t":"双单倍体"},"amphikaryon":{"p":",æmfi'kæriәn","t":"双组核, 倍数核, 受精核"},"amphilepsis":{"p":"æmfi'lepsis","t":"双亲遗传"},"amphilestidae":{"w":"Amphilestidae","t":"疑盗猬科"},"amphileucemic":"[医] 两向性白血病的","amphileukemic":"[医] 两向性白血病的","amphilinidea":{"w":"Amphilinidea","t":"两线目"},"amphimacer":{"p":"æm'fimәsә","t":"n. 扬抑扬格, 长短长格"},"amphimerus":{"w":"Amphimerus","t":"[医] 两边[吸虫]属"},"amphimerycidae":{"w":"Amphimerycidae","t":"疑刍驼科"},"amphimerycoidea":{"w":"Amphimerycoidea","t":"疑刍驼超科"},"amphimicrobe":"[医] 兼性厌氧微生物","amphimicrobian":"[医] 兼性厌氧","amphimictic":{"p":",æmfi'miktik","t":"a. [生]两性融合的,杂交繁育的"},"amphimixis":{"p":".æmfi'miksis","t":"n. 两性融合, 杂交繁育\\n[医] 两性融合"},"amphimonadidae":{"w":"Amphimonadidae","t":"双鞭滴虫科"},"amphimorphic":"二重","amphimorula":"[医] 两歧桑胚","amphineura":{"w":"Amphineura","p":",æmfi'njjәrә","t":"[复] n.[动]双神经纲"},"amphinucleolus":"[医] 双核仁, 染色质核仁","amphinucleus":"[医] 双质核, 中心核, 中央核","amphioblous":"暧昧的","amphion":{"w":"Amphion","p":"æm'faiәn","t":"n. [希神]安菲翁(宙斯之子)"},"amphiont":{"p":"'æmfiɔnt","t":"接合体"},"amphioxidae":{"w":"Amphioxidae","t":"[网络] 文昌鱼科"},"amphioxus":{"p":".æmfi'ɒksәs","t":"n. 文昌鱼\\n[医] 蛞蝓, 文昌鱼"},"amphipath":"两歧性分子","amphipathic":{"p":",æmfi'pæθik","t":"a. [生化]两性分子的 (=amphiphilic)"},"amphipathy":"[化] 两亲性","amphipeptone":"[医] 两性胨","amphiphile":"[化] 两亲物","amphiphilic":{"p":",æmfi'filik","t":"a. [生化]两性分子的"},"amphiphloic":"双韧的","amphiphyte":{"p":"'æmfifait","t":"n. 两栖植物"},"amphiplatyan":"两端平的; 双平型","amphiploid":{"p":"'æmfiplɔid","t":"a. 具有双倍体的"},"amphiploidy":{"p":"æm'fɪpləʊɪdɪ","t":"[医]双倍体性"},"amphipneustic":"双唿吸型","amphipnile":"两歧性分子","amphipod":{"p":"'æmfipɔd","t":"n. 片脚类动物"},"amphipoda":{"p":"'æmfipɔdə","t":"n. 端足类"},"amphipodous":{"p":"æm'fipədəs","t":"a. amphipod的变形"},"amphipods":"(amphipod 的第三人称 -s形式) n.片脚类动物","amphiporids":"双孔层孔虫","amphiporine":"[医] 纽虫烟硷","amphiposition":"[化] 远位; 跨位(萘环的2,6位)","amphiprion":{"w":"Amphiprion","t":"[网络] 双锯鱼属；海葵鱼属；双锯齿盖鱼属"},"amphiprostyle":{"p":"æm'fiprәustail","t":"n. [建]前后两排柱而两边无柱的建筑"},"amphiprostylos":"前后列柱式","amphiprotic":"[化] 两性的","amphipsylla":{"w":"Amphipsylla","t":"[医] 双蚤属"},"amphipyrenin":"[医] 核膜质","amphirrhina":{"w":"Amphirrhina","t":"[医] 两鼻类"},"amphisapropel":"半腐泥","amphisarca":"瓜果","amphisbaena":{"p":".æmfis'bi:nә","t":"n. 两头蛇, 蚓蜥属"},"amphisbaenia":{"w":"Amphisbaenia","t":"[网络] 蚓蜥亚目；蚯蜥；蚓蜥类"},"amphisbaenian":{"p":",æmfis'bi:niәn","t":"n. & adj.[动]蚓蜥(的)"},"amphisbaenians":"(amphisbaenian 的复数) n.& adj.[动]蚓蜥(的)","amphisbaenic":{"p":",æmfis'bi:nik","t":"amphisbaena的变形"},"amphisbaenidae":{"w":"Amphisbaenidae","p":",æmfis'bi:nədi:","t":"n. 蚓蜥科"},"amphisbaenoid":{"p":",æmfis'bi:nɔid","t":"amphisbaena的变形"},"amphiscians":{"p":"æm'fiʃiənz; æm'fiʃii","t":"n. [复数][古语]热带居民, 热带民族"},"amphiscii":{"p":"æm'fiʃiənz; æm'fiʃii","t":"n. [复数][古语]热带居民, 热带民族"},"amphisopidae":{"w":"Amphisopidae","t":"双等足科"},"amphispore":"休眠夏孢子","amphissitidae":{"w":"Amphissitidae","t":"双绿介科"},"amphistaenidae":{"w":"Amphistaenidae","t":"蚓蜥科"},"amphistoma":{"w":"Amphistoma","t":"[医] 端盘[吸虫]属, 双口吸虫属"},"amphistomata":{"w":"Amphistomata","t":"[医] 端盘[吸虫]亚目"},"amphistome":{"p":"'æmfistәum","t":"端盘吸虫"},"amphistomiasis":{"p":",æmfistәu'maiәsis","t":"端盘吸虫病, 双口吸虫病"},"amphistomous":{"p":"æmfi'stəməs","t":"a. 【植物学】两面气孔的；【动物】端盘亚目的"},"amphistomus":{"p":"æm'fistәmәs","t":"有端吸盘的"},"amphistylar":{"p":",æmfi'stailә","t":"a. [建]前后两排柱而两边无柱的(建筑)的"},"amphistylic":{"p":",æmfi'stailik","t":"双接型, 两接型"},"amphistyly":{"p":",æmfi'staili","t":"两接型"},"amphitene":{"p":"'æmfi,ti:n","t":"[生]合线, 偶线期"},"amphithalite":{"p":"æm'fiθә,lait","t":"艳冠石"},"amphithallism":{"p":",æmfi'θælizm","t":"同宗异宗配合(现象)"},"amphitheater":{"p":"'æmfi.θiәtә","t":"n. 圆形剧场, 竞技场, 梯形看台"},"amphitheaters":"(amphitheater 的复数) n. 圆形剧场, 竞技场, 梯形看台","amphitheatral":{"p":",æmfi'θiәtrәl","t":"a. 圆剧场(式)的"},"amphitheatre":"圆形剧场, 大会堂, 比赛场, 露天竞技场\\n[医] 手术示教室, 看台式教室","amphitheatres":{"p":"ˈæmfθətəz","t":"n. 圆形露天竞技场( amphitheatre的复数形式 )"},"amphitheatric":{"p":",æmfiθi'ætrikl","t":"a. 圆剧场(式)的"},"amphitheatrical":{"p":",æmfiθi'ætrikl","t":"a. 圆剧场式的"},"amphitheatrically":{"p":",æmfiθi'ætrikəli","t":"adv. amphitheatre, amphitheater的变形"},"amphithecium":{"p":",æmfi'θi:siәm","t":"n. [植]细胞外层,蒴周层"},"amphithymia":"[医] 双重情感","amphitokal":"[医] 单体两性生殖的","amphitoky":"[医] 单体两性生殖","amphitriaene":"双三叉体","amphitricha":"[医] 两端鞭毛菌","amphitrichate":"[医] 有两端鞭毛的","amphitrichous":"[医] 两端鞭毛的","amphitrite":{"w":"Amphitrite","p":"'æmfitraiti","t":"n. [希神]安菲特律特(海中50仙女之一,海的女神,海神Poseidon之妻)"},"amphitritinae":{"w":"Amphitritinae","t":"须头虫科"},"amphitrocha":"双轮幼虫","amphitropic":"[医] 横生的","amphitropous":{"p":"æm'fitrәpәs","t":"a. 植物横生的"},"amphitryon":{"w":"Amphitryon","p":"æm'fitriәn","t":"n. 安菲特律翁(底比斯王)"},"amphitypy":"[医] 两型[状态]","amphiuma":"[医]有尾类，两栖螈属","amphiumidae":{"w":"Amphiumidae","t":"两栖螈科"},"amphivalency":"[化] 异配现象","amphivasal":"週木的","amphizoidae":{"w":"Amphizoidae","t":"两栖甲科"},"amphlet":"[人名] 安弗利特","amphochromatophil":"[医] 两染性的, 两染细胞","amphochromophil":"[医] 两染性的, 两染细胞","amphocillin":"[医] 安福西林(口服青霉素制剂)","amphocyte":"[医] 两染细胞","amphodelite":{"p":"æm'fәudilait","t":"钙长石"},"amphodiplopia":{"p":",æmfәdi'plәupiә","t":"(=amphoterodiplopia)两眼复视"},"amphogenic":"[医] 两性生殖的","amphojel":"[医] 安福杰耳(氢氧化铝凝胶)","ampholyte":{"p":"'æmfәlait","t":"n. 两性电解质"},"ampholyteric":"[机] 两性的","ampholytoid":{"p":",æmfә'litɔid","t":"(=amphoteric colloid)两性胶体"},"amphomate":"[医] 安福梅特(含樟脑酸的乌洛托品注射剂)","amphomoronal":"二性霉素B","amphomycin":"[化] 安福霉素; 双霉素; 颖霉素\\n[医] 双霉素","amphopeptone":"[医] 两性胨","amphophil":"[医] 两染性的, 两染细胞","amphophilic":"[医] 两染性的","amphophilous":"[医] 两染性的","amphora":{"p":"'æmfәrә","t":"[医] 瓶状体(植)"},"amphorae":"双耳细颈椭圆土罐( amphora的名词复数 )","amphoral":{"p":"'æmfərəl","t":"a. amphora的变形"},"amphoras":"(amphora 的复数) [医] 瓶状体(植)","amphoric":{"p":"æm'fɔrik","t":"a. 空洞音的, 瓮音的"},"amphoricity":"[医] 空瓮性","amphoriloquy":"[医] 空瓮性语音","amphoriscidae":{"w":"Amphoriscidae","t":"瓮海绵科"},"amphorophony":"[医] 空瓮性语音","amphosyndesis":"[医] 两样接合","amphotalide":"[化] 氨苯酞胺","amphotere":"[化] 两性元素","amphoteric":{"p":".æmfә'terik","t":"a. 两性的\\n[化] 两性的; 兼性的"},"amphotericin":{"p":",æmfә'terәsin","t":"[医] 两性霉素"},"amphotericity":"[医] 两性, 酸硷兼性","amphoterics":"[化] 两性表面活性剂","amphoterism":"[化] 两性现象; 两性性质\\n[医] 两性, 酸硷兼性","amphoterite":"无粒古铜橄榄陨石","amphoterodiplopia":"[医] 两眼复视","amphoterous":"[医] 两性的, 酸硷兼性的","amphotony":"[医] 交感迷走神经过敏","amphotropin":"[医] 安福托品(乌洛托品、樟脑注射剂)","amphotropine":"[机] 安福托品","amphozone":"[化] 两性霉素B","amphtrac":"水陆履带牵引车","amphyl":"酚衍生物","ampicillin":{"p":",æmpi'silin","t":"n. 氨苄青霉素\\n[化] 氨苄西林; 氨苄青霉素"},"ampiclla":"坛囊","amping":"(amp 的现在分词) n. 安培\\n[化] 腺苷酸; 腺苷一磷酸","ample":{"p":"'æmpl","t":"a. 大量的, 充足的, 丰富的"},"amplectant":{"p":"æm'plektәnt","t":"a. 攀附的"},"ampleforth":{"w":"Ampleforth","t":"n. (Ampleforth)人名；(英)安普尔福思"},"ampleness":"n. 充分, 绰绰有余, 富裕, 足够, 宽大, 宽敞","ampler":"(ample 的比较级) a. 大量的, 充足的, 丰富的","amplest":"ample的最高级","amplexation":"[医] [锁骨骨折]围合疗术","amplexicaul":{"p":"æm'pleksi,kɔ:l","t":"a. [植]抱茎的"},"amplexiform":"贴接","amplexis":"抱接","amplexus":{"p":"æm'pleksәs","t":"n. [动]抱合(指雌的蛙或蟾产卵于水时雄的蛙或蟾抱合排精的求偶行动)"},"ampli":"n. (Ampli)人名；(俄)安普利","ampliate":{"p":"'æmpli'eit","t":"a. 广大的；放大的"},"ampliation":{"p":",æmpli'eiʃәn","t":"n. 扩大, 扩张,[律](民事案件的)延期裁决"},"ampliative":{"p":"'æmplieitiv","t":"a. 扩大的, 扩展的"},"amplidyne":{"p":"'æmpli,dain","t":"[电] 电动放大机"},"amplification":{"p":".æmplifi'keiʃәn","t":"n. 扩大, 放大\\n[化] 放大; 放大作用"},"amplifications":{"p":",æmplɪfɪ'keɪʃən","t":"n. [电子] 放大（率）；扩大；详述"},"amplificative":{"p":",æmpli'fikәtiv","t":"[逻]扩充的, [修]铺陈的, 增强词义的"},"amplificatory":{"p":"'æmplifikeitəri","t":"a. 放大的"},"amplified":"v. 放大；详述（amplify的过去分词）","amplifier":{"p":"'æmplifaiә","t":"n. 扩大的人(物), 放大器, 扩音器\\n[计] 放大器"},"amplifierinverter":"倒相放大器","amplifiers":{"p":"'æmplɪfaɪəz","t":"n. 扩音器( amplifier的复数形式 ); 放大器; 扩大的人; 详述者"},"amplifies":{"p":"ˈæmplifaiz","t":"v. 放大, 扩大( amplify的第三人称单数 ); 增强; 详述"},"amplifilter":"放大-泸波器","amplify":{"p":"'æmplifai","t":"vt. 增强, 放大, 扩大, 详述\\nvi. 引伸"},"amplifying":"[化] 放大的","ampligen":{"p":"'æmpliɡən","t":"n. 安普利近（药物名）"},"ampligraf":{"p":"'æmpli^rɑ:f","t":"摆幅仪"},"ampligraph":"摆幅记录仪","amplimeter":{"p":"'æmpli,mi:tә","t":"指针式摆幅仪"},"ampliscaler":{"p":"'æmpli,skeilә","t":"百定标电路"},"ampliscope":{"p":"'æmpli,skәup","t":"示波式摆幅仪"},"ampliscript":{"p":"'æmpli,skript","t":"摆幅仪"},"amplistat":{"p":"'æmplistæt","t":"[电] 磁性放大器的自饱和形式"},"amplitrans":{"p":"'æmplitræns","t":"特高频功率放大器(一种磁放大器)"},"amplitron":{"p":"'æmplitrɔn","t":"[电] 增幅管"},"amplitude":{"p":"'æmplitju:d","t":"n. 广阔, 充足, 幅度\\n[化] 振幅"},"amplitudes":"(amplitude 的复数) n. 广阔, 充足, 幅度\\n[化] 振幅","amplum":{"w":"Amplum","t":"安普纶"},"amply":{"p":"'æmpli","t":"adv. 充足地, 充裕地"},"ampm":"麦芽制品生产商协会（association of malt products manufacturers）","amporphous":"非晶形","ampoul":"[化] 安瓿; 针药管; 安瓿剂; 针药; 壶腹","ampoule":{"p":"'æmpu:l","t":"n. 安瓿\\n[化] 安瓿; 针药管; 安瓿剂; 针药; 壶腹"},"ampoules":{"p":"ˈæmpu:lz","t":"n. 一次用量的针剂, 安瓿( ampoule的复数形式 )"},"amprolium":"[化] 安普罗铵; 氨丙啉","amprotropine":"[医] 安颇托品, 辛托潘, 合成托潘(解痉药)","amps":{"w":"AMPS","t":"[计] 高级移动电话业务"},"ampudia":"[地名] [西班牙] 安普迪亚","ampul":{"p":"'æmpjl","t":"n. 安瓿(=ampoule)"},"ampule":{"p":"'æmpul","t":"n. 安瓿\\n[医] 安瓿"},"ampules":{"p":"'æmpul, 'æmpju:l","t":"n. [药] 安瓿（等于ampoule）"},"ampulicidae":{"w":"Ampulicidae","t":"长背泥蜂科"},"ampulla":{"p":"æm'pulә","t":"n. 两耳细颈瓶, (教堂)圣瓶\\n[医] 安瓿[剂], 壶腹"},"ampullaceal":"坛形的","ampullaceous":{"p":",æmpә'leiʃәs","t":"a. 瓶状的"},"ampullae":"[医] 安瓿[剂], 壶腹","ampullar":"[医] 壶腹的, 壶腹状的","ampullaria":{"w":"Ampullaria","t":"[医] 壶螺属"},"ampullary":"[医] 壶腹的, 壶腹状的","ampullate":"[医] 壶腹状的","ampulliform":"安瓿形的","ampullitis":"[医] 壶腹炎","ampullula":"[医] 小壶腹","amputate":{"p":"'æmpjuteit","t":"vt. 切断, 删除"},"amputated":"切断\\n锯掉\\n截（肢）（amputate的过去式和过去分词）","amputates":{"p":"ˈæmpjʊˌteɪts","t":"v. （用外科手术）截（肢等）( amputate的第三人称单数 ); 切断; 砍掉; 删除"},"amputating":"a. 切断的\\nv. 切断；砍掉（amputate的ing形式）","amputation":{"p":".æmpju'teiʃәn","t":"n. 切断, 截肢术\\n[医] 切断术"},"amputations":"(amputation 的复数) n. 切断, 截肢术\\n[医] 切断术","amputator":{"p":"'æmpjuteitә","t":"n. 施行切断手术者, 施行截肢手术者"},"amputee":{"p":".æmpju'ti:","t":"n. 被截肢者\\n[医] 切肢者"},"amputees":"(amputee 的复数) n. 被截肢者\\n[医] 切肢者","ampyrimine":"安匹立明","ampyrone":"[化] ; 氨基安替比林","amr":"abbr. 自动执息路由；美利坚公司美国航空公司；材料提前公布（Advanced Material Release）","amra":"abbr. 美国医学档案协会（american medical record association）","amraam":"abbr. 先进中程空对空导弹（Advanced Medium-Range Air-To-Air Missile）","amram":"阿姆拉姆（人名）","amrc":"abbr. Advanced Metals Research Corporation 高级金属研究有限公司; Army Mathematics Research Center <美国>陆军数学研究中心; American Mobile Radio Corp. 美国移动无线通信公司; Automotive Market Research Council 汽车销路研究协会","amre":"n. (Amre)人名；(意)阿姆雷","amrhein":"n. (Amrhein)人名；(德)阿姆赖因","amri":{"p":"'æmri","t":"n. 阿姆里（巴基斯坦一城市）"},"amrinone":"[化] 氨力农","amrit":"n. (Amrit)人名；(印)阿姆里特","amrita":{"p":"әm'ri:tә","t":"n. 长生不老的仙露,甘露"},"amritsar":{"w":"Amritsar","p":",ʌm'ritsә(r)","t":"阿姆利则[印度北部城市](锡克教圣地)"},"amro":"n. (Amro)人名；(阿拉伯、埃塞)阿姆鲁\\nabbr. 医学档案员协会（association of medical record officers）","ams":{"w":"AMS","t":"[计] 存取方法服务, 财务管理系统, 行政管理协会, 应用管理服务\\n             应用管理系统, 应用绘图服务, 非对称多处理系统"},"amsa":"abbr. 澳大利亚海洋科学协会（australian marine science association）","amsacrine":"[化] 安吖啶","amschel":"[人名] 阿姆谢尔","amsden":"n. (Amsden)人名；(英)阿姆斯登","amsdorf":"[地名] [德国] 阿姆斯多夫","amsel":"n. (Amsel)人名；(德、英)阿姆泽尔","amsellem":"n. (Amsellem)人名；(法)安塞朗","amsinckia":{"w":"Amsinckia","t":"[网络] 琴颈草属；阿姆辛基属"},"amsler":"n. (Amsler)人名；(德)阿姆斯勒","amsonia":{"w":"Amsonia","t":"[医] 水甘草"},"amstel":"阿姆斯特尔河","amster":"n. (Amster)人名；(德、英、西)阿姆斯特","amsterdam":{"w":"Amsterdam","p":".æmstә'dæm","t":"n. 阿姆斯特丹(荷兰首都)"},"amsterdammer":{"w":"Amsterdammer","p":"ˈæmstəˈdæm","t":"阿姆斯特丹(荷兰首都, 港市) [亦见 The Hague]；阿姆斯特丹(美国纽约州东部城市)"},"amsterdams":{"p":"ˈæmstəˈdæm","t":"n. 阿姆斯特丹（荷兰首都）；阿姆斯特丹（美国纽约东部城市）"},"amstutz":"[人名] 阿姆斯特茨","amt":{"p":"ɑ:mt","t":"abbr. 数量, 总额（amount）"},"amta":"abbr. 美国按摩与治疗协会（american massage and therapy association）","amte":"abbr. Admiralty Marine Technology Establishment 英国海军海洋技术研究所","amter":{"p":"'ɑ:mtə","t":"n. amt的变形"},"amti":"空载移动目标显示（airborne moving target indication）","amtifebrin":"[机] 退热冰","amtifertilizin":"[机] 反受精素","amtition":"野心","amtorg":{"w":"Amtorg","p":"'æmtɔ:^","t":"n. (苏联设在美国的)苏美贸易公司"},"amtr":"[医][=angiomesenchymal tissue reaction]血管间质组织反应","amtrac":{"p":"'æmtræk","t":"n. 水陆两用车"},"amtrack":{"w":"Amtrack","p":"'æmtræk","t":"(=American track)全国铁路客运公司[美]"},"amtracs":{"p":"'æmtræk","t":"n. 水陆两用车"},"amtrak":{"p":"'æmtræk","t":"abbr. 美国铁路公司（American track）"},"amu":"[电] 原子量单位的缩写","amuck":{"p":"ә'mʌk","t":"adv. 狂乱地, 杀气腾腾地\\na. 嗜杀的"},"amuda":"[地名] [尼日利亚、乌干达] 阿穆达","amul":"[地名] [伊朗] 阿莫勒","amulet":{"p":"'æmjulit","t":"n. 护身符"},"amulets":{"p":"ˈæmjəlɪts","t":"n. 护身符( amulet的复数形式 )"},"amun":"[地名] [巴布亚新几内] 阿蒙","amundsen":{"w":"Amundsen","p":"'ɑ:mjndsən","t":"Sea 阿蒙森海(南极洲的边缘海,在瑟斯顿岛同达尔特角之间,终年结冰)"},"amundson":"n. (Amundson)人名；(英)阿蒙森；(瑞典)阿蒙松","amur":{"w":"Amur","p":"ә'muә","t":"阿穆尔河(即黑龙江)"},"amurensis":"紫椴","amusable":"a. amuse的变形","amusd":{"w":"AMusD","t":"abbr. Doctor of Musical Arts 音乐博士"},"amuse":{"p":"ә'mju:z","t":"vt. 消遣, 娱乐, 使发笑"},"amused":{"p":"ә'mju:zd","t":"a. 愉快的, 被逗乐的"},"amusedly":{"p":"ә'mju:zidli","t":"adv. 愉快地, 被逗乐地"},"amusement":{"p":"ә'mju:zmәnt","t":"n. 兴味, 娱乐, 消遣\\n[法] 娱乐, 娱乐活动"},"amusements":{"p":"ˌəˈmju:zmənts","t":"n. 娱乐( amusement的复数形式 ); 乐趣; 娱乐活动; 文娱活动"},"amuser":"n. amuse的变形","amuses":{"p":"əˈmju:ziz","t":"v. 使人发笑( amuse的第三人称单数 ); 逗乐; 使消遣; 娱乐"},"amusette":"小玩意儿, 小游戏","amusia":{"p":"ә'mju:ziә","t":"n. [医]无歌唱能力,失歌症"},"amusing":{"p":"ә'mju:ziŋ","t":"a. 有趣的, 引人发笑的"},"amusingly":{"p":"ə'mju:zɪŋlɪ","t":"adv. 有趣地, 好笑地"},"amusingness":"n. amusing的变形","amusive":{"p":"ә'mju:ziv","t":"a. 有趣的, 令人愉快的"},"amv":"abbr. 机械辅助通气；成本价均线；自动磁偏角","amvets":{"w":"Amvets","p":"'æmvets","t":"n. 第二次世界大战美国退伍军人协会"},"amwa":{"p":"'æmwə","t":"[医][=american medical women's association]美国女医务工作者协会"},"amway":"n. 安利公司","amwell":"[人名] 阿姆韦尔","amy":{"p":"'eimi","t":"n. 艾米（女子名）"},"amyas":" [男子名] 埃米亚斯来源于拉丁语, 含义是“爱+上帝”(love+God)","amyasthenia":"[医] 肌无力","amyasthenic":"[医] 肌无力的","amycetin":"[医] 友霉素","amychophobia":"[医] 抓伤恐怖","amycin":"[化] 阿霉素","amyctic":{"p":"æ'miktik","t":"腐蚀性的, 刺激性的"},"amydriasis":{"p":",æmi'draiәsis","t":"瞳孔未扩大"},"amydricaine":"[化] 戊胺卡因","amyelencephalia":"[医] 无脑脊髓[畸形]","amyelencephalus":"[医] 无脑脊髓畸胎","amyelia":"[医] 无脊髓[畸形]","amyelic":"[医] 无脊髓的","amyelineuria":"[医] 脊髓机能缺失","amyelinic":"[医] 无髓鞘的","amyeloidemia":"[医] 无髓细胞血症","amyeloneuria":"[医] 脊髓机能缺失","amyelonic":"[医] 无脊髓的, 无骨髓的","amyelotrophy":"[医] 脊髓萎缩","amyelus":"[医] 无脊髓畸胎","amygdaiine":"[医] 杏形的, 扁桃形的, 扁桃体的","amygdala":{"p":"ә'migdәlә","t":"n. 巴旦杏, 扁桃, 扁桃体\\n[医] 苦扁桃, 苦巴旦杏, 扁桃体, 杏仁核"},"amygdalaceae":{"w":"Amygdalaceae","t":"[网络] 拟李科；桃科；扁桃科"},"amygdalaceous":{"p":"ә,mi^dә'leiʃәs","t":"a. 扁桃类的, 蔷薇科李属植物的"},"amygdalae":"amygdala的复数形","amygdalas":{"p":"ə'mɪgdələ","t":"n. [解剖] 杏仁核；扁桃腺；苦巴旦杏"},"amygdalase":{"p":"ә'mi^dә,leis","t":"苦杏仁苷酶, 扁桃苷分解酶, 苦杏仁酶"},"amygdalate":{"p":"ә'mi^dәlit","t":"a. 巴旦杏的, 巴旦杏状的"},"amygdale":{"p":"ә'mi^deil","t":"n. [矿] 杏仁孔"},"amygdalectomy":{"p":"ә,mi^dә'lektәmi","t":"扁桃体切除术"},"amygdaliform":{"p":"ə'mɪɡdɑ:lɪfɔ:m","t":"[医]扁桃状"},"amygdalin":{"p":"ә'mi^dәlin","t":"n. [生化]苦杏苷, 杏苷"},"amygdaline":{"p":"ә'mi^dә,lain","t":"a. 杏仁的, 似杏仁的"},"amygdalitis":"[医] 扁桃体炎","amygdaloid":{"p":"ә'mi^dәlɔid","t":"n. 杏仁岩\\na. 杏仁状的, 似杏仁岩的"},"amygdaloidal":{"p":"ә,mi^dә'lɔidəl","t":"a. 杏仁岩 (=amygdaloid)"},"amygdalolith":"[医] 扁桃体石","amygdaloncus":"[医] 扁桃体瘤","amygdalopathy":"[医] 扁桃体病","amygdalophenin":"[医] 杏仁酰对乙氧基苯胺","amygdalose":"[医] 苦杏仁糖","amygdalothrypsis":"[医] 扁桃体压碎术","amygdalotome":"[医] 扁桃体刀","amygdalotomies":{"p":"ə,miɡdə'lɔtəmi","t":"n. 【医学】扁桃体部分切除术"},"amygdalotomy":{"p":"ә,mi^dә'lɔtәmi","t":"n. [医]扁桃体部分切除术"},"amygdalthrypsis":"扁桃体压碎术","amygdalus":{"w":"Amygdalus","t":"桃属\\n扁桃属"},"amygdophenin":"[医] 杏仁酰对乙氧基苯胺","amygdule":{"p":"ә'mi^du:l","t":"n. 杏仁孔"},"amyl":{"p":"'æmil","t":"n. 戊基\\n[化] 戊基"},"amylaceous":{"p":".æmi'leiʃәs","t":"a. 淀粉的, 淀粉状的\\n[医] 淀粉的"},"amylacetylene":"[化] 戊基乙炔; 庚炔","amylaceum":"[医] 葡萄糖","amylaemia":"[医] 淀粉血症","amylamine":{"p":",æmi'læmin","t":"戊胺, 戊基胺"},"amylan":"[化] 麦胶","amylase":{"p":"'æmileis","t":"n. 淀粉酶\\n[化] 淀粉酶"},"amylases":{"p":"'æmɪleɪz","t":"n. [生化] 淀粉酶"},"amylatic":{"p":",æmi'lætik","t":"水解淀粉的, 淀粉变糖的"},"amylbenzene":{"p":",æmil'benzi:n","t":"戊基苯(通指正戊基苯)"},"amylbiguanide":"[医] 戊烷双胍","amylcaine":"[医] 戊卡因","amylemia":"[医] 淀粉血症","amylene":{"p":"'æmili:n","t":"n. [化]戊烯"},"amylenization":{"p":",æmәli:ni'zeiʃәn","t":"戊烯麻醉"},"amylic":"[医] 戊基的","amylidene":"[化] 1,1-亚戊基","amylin":"[化] 糊精\\n[医] 淀粉不溶素, 淀粉经络质","amyline":"[化] 淀粉粒的纤维素膜","amylis":{"p":"'æmilis","t":"戊基(amyl 的拉丁名称)"},"amylism":{"p":"'æmilizәm","t":"戊醇中毒"},"amylit":{"p":"'æmilit","t":"麦芽糖化酶"},"amylobacter":"[医] 淀粉杆菌","amylobarbitone":{"p":",æmilәj'bɑ:bitәjn","t":"n. <英>戊巴比妥(一种镇静催眠药)"},"amylocaine":"[医] 阿米洛卡因, 斯妥伐因(局部麻醉药)","amylocainehydrochloride":"[化] 盐酸阿米卡因; 盐酸异戊卡因","amylocellulose":{"p":",æmilәu'seljәulәus","t":"直链淀粉, 含淀粉纤维素"},"amyloclast":{"p":",æmilәu'klæst","t":"淀粉分解酶, 分解淀粉酵素"},"amyloclastic":{"p":",æmilәu'klɑ:stik","t":"(=amylolytic)能分解淀粉的"},"amylocoagulase":"[医] 淀粉凝固酶","amylocyanin":"[化] 淀粉蓝素\\n[医] 菌淀粉青素","amylodextrin":"[化] 淀粉糊精; 极限糊精\\n[医] 淀粉糊精","amylodyspepsia":"[医] 淀粉消化不良","amyloform":"[化] 淀粉仿; 淀粉甲醛混合物\\n[医] 甲醛淀粉, 淀粉仿","amylogen":{"p":"ә'milәdʒәn","t":"n. [化]淀粉溶质"},"amylogenesis":{"p":",æmilәu'dʒenisis","t":"淀粉形成(作用)"},"amylogenic":"[医] 生成淀粉的","amyloglucosidase":"[机] 淀粉葡糖甘","amylograph":{"p":"'æmilәu,^rɑ:f","t":"(淀粉)粘焙力测量器, 面糊粘度测量法"},"amylohemicellulose":"[医] 类直链淀粉","amylohydrolysis":{"p":",æmilәu,hai'drɔlisis","t":"淀粉水解"},"amyloid":{"p":"'æmilɒid","t":"a. 淀粉的, 含淀粉的\\nn. 淀粉质食物, 淀粉状蛋白"},"amyloidal":{"p":",æmi'lɔidəl","t":"a. 淀粉质的, 含淀粉的(=amyloid)"},"amyloidemia":"[医] 淀粉样蛋白血[症]","amyloidopathia":"[医] 淀粉样病, 淀粉样蛋白病","amyloidosis":{"p":",æmilɔi'dәjsis","t":"[医] 淀粉样变性"},"amyloin":"[化] 麦芽糖糊精","amyloins":{"p":",æmi'lɔins","t":"麦芽糖糊精与不同比例麦芽糖的复合体"},"amylolysis":{"p":",æmi'lɔlisis","t":"n. 淀粉分解"},"amylolytic":{"p":",æmә'lәlitik","t":"a. 淀粉分解的"},"amylomaltose":{"p":",æmilә'mɔ:ltәus","t":"麦芽糖"},"amylometer":"淀粉计","amylomyces":{"p":",æmilәu'maisi:z","t":"淀粉霉, 属糖化菌[酶]"},"amylomycin":{"p":",æmilәu'maisin","t":"真菌淀粉"},"amylon":{"p":"'æmilɔn","t":"淀粉"},"amylopectase":"[化] 支链淀粉酶\\n[医] 支链淀粉酶","amylopectin":{"p":",æmilәu'pektin","t":"n. [生化]支链淀粉,胶淀粉"},"amylopectinosis":"支链淀粉病","amylophagia":"[医] 食淀粉癖","amylophosphatase":"[医] 淀粉磷酸酶","amylophosphorylase":"[医] 淀粉磷酸化酶","amyloplast":"[医] 淀粉形成体, 造粉体","amyloplastic":"[医] 造成淀粉的","amyloprolamine":{"p":",æmilәu'prәulәmin","t":"麦蛋白"},"amylopsin":{"p":".æmi'lɒpsin","t":"n. 胰淀粉酶\\n[化] 胰淀粉酶"},"amylorrhea":"[医] 淀粉溢(粪便中)","amylorrhexis":{"p":",æmilәu'reksis","t":"淀粉酶水解[作用]"},"amylose":{"p":"'æmilous","t":"n. 直链淀粉, 多糖\\n[化] 直链淀粉"},"amylosis":"[医] 蛋白样变性","amylostatolith":"淀粉平衡石","amylosuria":"[医] 淀粉尿","amylosynthease":"[医] 淀粉合成酶","amylosynthesis":{"p":",æmilәu'sinθisis","t":"淀粉合成作用"},"amyloysis":"[化] 淀粉分解","amyltal":{"w":"Amyltal","t":"[机] 阿米妥"},"amylum":{"p":"'æmilәm","t":"n. 淀粉\\n[化] 淀粉"},"amyluria":"[医] 淀粉尿","amylzyme":"[医] 淀粉酶","amynodontidae":{"w":"Amynodontidae","t":"两栖犀科"},"amynologic":"[医] 免疫学的","amynology":"[医] 免疫学","amyntas":"阿闵塔斯","amyocardia":{"p":"ә,maiә'kɑ:diә","t":"心肌无力"},"amyoplasia":"[医] 肌发育不全","amyostasia":"[医] 肌静止不能, 肌震颤","amyostatic":"[医] 肌静止不能的, 肌震颤的","amyosthenia":"[医] 肌无力","amyosthenic":"[医] 肌无力的","amyot":"n. (Amyot)人名；(英)阿米欧；(法)阿米约","amyotaxia":"[医] 肌共济失调","amyotaxy":"[医] 肌共济失调","amyotonia":{"p":",eimaiә'tәuniә","t":"n. 肌弛缓\\n[医] 肌驰缓"},"amyotrophia":{"p":",eimaiә'trәufiә","t":"n. 肌萎缩"},"amyotrophic":"[医] 肌萎缩的","amyotrophy":"[医] 肌萎缩","amyous":"[医] 无肌的","amyradiene":"白檀二烯","amyrenone":"白檀酮","amyrin":"香树精; 香树脂醇","amyris":{"w":"Amyris","t":"[医] 阿米香树属"},"amyrol":"[医] 白檀油醇","amyrone":"白檀酮","amys":"(amy 的复数) n. 艾米（女子名）","amytal":{"w":"Amytal","p":"'æmitæl","t":"n. [药]阿米妥,异戊巴比妥(商标名,镇静催眠药)"},"amyx":"[人名] 阿米克斯","amyxia":{"p":"ei'miksiә","t":"(=amyxorrhea)粘液缺乏"},"amyxis":{"p":"ei'miksis","t":"划痕, 划破"},"amyxorrhea":"[医] 粘液分泌缺乏","amzn":"abbr. 亚马逊（美国纳斯达克的股票代码，Amazon）"}