{"eg":"abbr. [拉]例如（exempli gratia）；[网络用语]邪恶的笑（Evil Grin）","ega":{"w":"EGA","t":"增强型图形适配器"},"egad":{"p":"i:'^æd","t":"int. 天哪, 哎呀"},"egads":{"p":"ɪ'ɡædz","t":"abbr. electronic ground automatic destruct sequencer (system for destroying malfunctioning missiles) 电子地面自动破坏程序装置（故障导弹摧毁系统）"},"egagropilus":"[医] 毛团, 毛块","egal":{"p":"ɪ'ɡæl","t":"abbr. egalitarian 平等主义的, 平等主义"},"egalitarian":{"p":"i.gæli'tєәriәn","t":"a. 平等主义的\\nn. 平等主义"},"egalitarianism":{"p":"i.ɡæli'tεәriәnizәm","t":"n. 平等主义, 平均主义"},"egalitarians":"(egalitarian 的复数) a. 平等主义的\\nn. 平等主义","egalite":"[网络] 平等；平等之爱起泡酒","egality":{"p":"ɪ'ɡælɪtɪ","t":"n. 平等, 均等"},"egan":{"w":"Egan","t":"n. 伊根（爱尔兰人名）\\nn. 伊根（地名, 在美国）"},"egasiology":"[医] 客观精神生物学","egast":{"p":"iːˊgest","t":"vt. 排洩"},"egbe":"[地名] [尼日利亚] 埃贝","egbert":{"w":"Egbert","t":"n. 埃格伯特（人名）"},"egc":{"p":"'ek","t":"abbr. electrogalvanized coated 电镀锌的; enterotoxin gene cluster 肠毒素基因簇"},"egcg":"abbr. epigallocatechin gallate 表儿茶素，表没食子酸盐","egcs":"(egc 的复数) abbr. electrogalvanized coated 电镀锌的; enterotoxin gene cluster 肠毒素基因簇","ege":"abbr. eau; gaz; electricite (French=water, gas, electricity) （法语）水; expected grade equivalent 预计级别当量","egeland":"[地名] [美国] 伊杰兰","egemen":"n. (Egemen)人名；(土)埃盖曼","eger":{"p":"'i:ɡə","t":"[人名] 埃杰; [地名] [德国] 埃格河"},"egeria":{"w":"Egeria","p":"i:'dʒiәriә","t":"n. 女顾问"},"egerman":"[人名] 埃格曼","egersimeter":"[医] 电激相应计(肌肉神经兴奋性及其时值测定器)","egersis":"[医] 警醒, 不眠","egerton":{"w":"Egerton","t":"n. (Egerton)人名；(英)埃杰顿"},"egest":{"p":"i:'gest","t":"vt. 排泄\\n[医] 排泄, 排出"},"egesta":{"p":"i:'dʒestә","t":"n. 排泄物"},"egested":{"p":"i:ˈdʒestid","t":"v. 排泄( egest的过去式和过去分词 )"},"egesting":{"p":"i:ˈdʒestɪŋ","t":"v. 排泄( egest的现在分词 )"},"egestion":"[医] 排泄","egestive":"a. egest的变形","egests":{"p":"i:ˈdʒests","t":"v. 排泄( egest的第三人称单数 )"},"egf":"abbr. 上表皮生长因素（Epidermal Growth Factor）","egfr":"[医][=epidermal growth factor receptor]表皮生长因子受体","egg":{"p":"eg","t":"n. 蛋, 卵\\nvt. 挑唆, 煽动, 调蛋黄"},"eggan":"[人名] 埃根; [地名] [尼日利亚] 埃甘","eggar":{"w":"Eggar","p":"'e^ә(r)","t":"幼虫食叶子的蛾类,搜集鸡蛋的人"},"eggars":{"w":"Eggars","t":"(Eggar 的复数) 幼虫食叶子的蛾类,搜集鸡蛋的人"},"eggbeater":{"p":"'egbi:tә","t":"n. 打蛋器"},"eggcup":{"p":"'egkʌp","t":"n. 蛋杯"},"eggcups":{"p":"'eɡkʌp","t":"n. 蛋杯（吃鸡蛋用的）"},"egged":"v. 煽动, 挑唆；用蛋黄蛋白调拌（egg的过去分词形式）","egger":{"p":"'e^ә(r)","t":"幼虫食叶子的蛾类,搜集鸡蛋的人"},"eggers":"埃格斯","eggert":"[人名] 埃格特; [地名] [冰岛] 埃盖特山","eggfruit":{"p":"eɡf'ru:t","t":"蛋黄果"},"egghead":{"p":"'eghed","t":"n. 有知识的人, 受过高等教育的人, 自以为有大学问的人"},"eggheaded":{"p":"'e^,hedid","t":"a. 书呆子的,书生气十足的"},"eggheadedness":{"p":"'eɡhedɪdnəs","t":"n. 书呆子"},"eggheads":{"p":"ˈeɡhedz","t":"n. 有知识者, 受过高等教育的人, 理论家( egghead的复数形式 )"},"egghot":{"p":"'eɡhɒt","t":"[医]热鸡蛋酒"},"egging":"vt. 煽动, 怂恿（egg的现在分词形式）\\nn. 在烹调中将蛋混入或敷在食品表面","eggler":{"p":"'eɡlə","t":"abbr. egg+dealer (an egg dealer) 鸡蛋经销商"},"eggless":{"p":"'eɡlɪs","t":"不产卵的"},"eggleston":{"w":"Eggleston","t":"n. (Eggleston)人名；(英)埃格尔斯顿"},"eggleton":" [人名] [英格兰人姓氏] 埃格尔顿住所名称，来源于古英语人名，含义是“刃，尖+狼”(edge,point+wolf)+古英语，含义是“圈用地，居留地”(enclosure,settlement)","eggnog":{"p":"ˈegnɒg","t":"n. （—杯）蛋奶酒; 蛋酒"},"eggplant":{"p":"'egplɑ:nt","t":"n. 茄子"},"eggplants":{"p":"'eɡplɑ:nts","t":"n. 茄子( eggplant的复数形式 )"},"eggs":"n. 鸡蛋；蛋（egg的复数形式）","eggshake":"[网络] 蛋糕","eggshell":{"p":"'egʃel","t":"n. 蛋壳"},"eggshells":{"p":"ˈeɡʃelz","t":"n. 蛋壳, 易碎的东西( eggshell的复数形式 )"},"eggwhisk":"n. 打蛋器\\n[网络] 搅蛋器","eggwhites":{"p":"ˈeɡwaits","t":"n. 蛋白"},"eggy":{"p":"ˈeɡi","t":"a. 含有（打过的）蛋的； 有蛋的味道的"},"egholm":"[地名] [丹麦] 艾岛","egi":" [计]= End-of-Group Indicator,组尾指示符","egidio":"[人名] 埃吉迪奥","egil":"[人名] 埃吉尔","egilops":{"p":"'i: dʒilɔps,'edʒi-","t":"n. [医]内脓肿穿破"},"egis":{"p":"'i:dʒis","t":"n. 保护, 维护"},"eglaf":null,"eglandular":"[医] 无腺的","eglandulose":{"p":"eɡ'lændjʊləʊs","t":" [医]无腺体的, 无腺的"},"eglandulous":"[医] 无腺的","eglantine":{"p":"'eglәntain","t":"n. 多花蔷薇\\n[化] α-甲苯甲酸异丁酯; 苯乙酸异丁酯"},"eglatere":{"p":"'eɡlətɪə","t":"n. [废语]=eglantine"},"egle":"[人名] 埃格尔","egles":"(egle 的复数)  [人名] 埃格尔","egleston":"[人名] [英格兰人姓氏] 埃格尔斯顿 Eggleston的变体","eglestonite":{"p":"'e^әlstәnait","t":"n. [矿]氯汞矿"},"eglevsky":{"w":"Eglevsky","t":"[网络] 埃格列夫斯基"},"eglin":{"p":"'eɡlɪn","t":"[医]水蛭（蛋白酶）抑制剂[可抑制弹性蛋白酶、组织蛋白酶G等]"},"egling":"[地名] [德国] 埃格灵","eglinton":{"w":"Eglinton","t":"n. (Eglinton)人名；(英)埃格林顿"},"eglise":"n. (Eglise)人名；(法)埃格利斯","eglises":"(eglise 的第三人称 -s形式) n. (Eglise)人名；(法)埃格利斯","egloff":"[人名] 埃格洛夫","eglomise":"n. 镜画","egmont":{"w":"Egmont","t":"埃格蒙特（男子名）"},"egner":"[人名] 埃格纳","ego":{"p":"'egәu. 'i:gәu","t":"n. 自我\\n[医] 自我"},"egoboo":{"p":"'i:^әjbu:,'e^-","t":"n. 自我赏识"},"egobronchophony":"[医] 支气管羊音","egocentric":{"p":".egәu'sentrik","t":"a. 自我中心的, 利己主义的\\nn. 利己主义者"},"egocentrically":"自我中心地; 利己地","egocentricities":"(egocentricity 的复数) n. 自我中心, 自私自利\\n[医] 自我中心","egocentricity":{"p":",e^әjsen'trisәti","t":"n. 自我中心, 自私自利\\n[医] 自我中心"},"egocentrics":"(egocentric 的复数) a. 自我中心的, 利己主义的\\nn. 利己主义者","egocentrism":"[医] 利己主义, 唯我主义","egodefense":{"p":"'i:^әjdi'fens,'e^-","t":"n. <美>[心] 自我防御"},"egodystonic":{"p":",i:^әjdis'tɔnik,,e^-","t":"a. [心]自我失调的,与自我不相容的"},"egoeroticism":"[医] 自体性欲","egoinvolvement":{"p":",i:^әjin'vɔlvmәnt,,e^-","t":"n. [心]自我介入(精神分析学派用语)"},"egoism":{"p":"'egәuizm","t":"n. 自我主义, 利己主义"},"egoisms":"(egoism 的复数) n. 自我主义, 利己主义","egoist":{"p":"'egәuist","t":"n. 自我主义者, 利己主义者"},"egoistic":{"p":".egәu'istik","t":"a. 自我中心的, 自私自利的"},"egoistical":{"p":".egәu'istikәl","t":"a. 自我中心的, 自私自利的"},"egoistically":{"p":".egәu'istikli","t":"adv. 利己地, 任性地"},"egoists":{"p":"ˈi:ɡəuists","t":"n. 自我主义者( egoist的复数形式 )"},"egoless":"[计] 无私的, 无我的, 他人的","egolf":"[人名] 埃戈夫","egomania":{"p":".egәu'meiniә","t":"n. 极端利己, 自大狂\\n[医] 利己狂, 自尊癖"},"egomaniac":{"p":",i:^әj'meinjæk,,e^-","t":"n. 极端利己主义者"},"egomaniacal":{"p":",i:^әjmә'naiәkәl","t":"a. 极端利己的"},"egomaniacally":{"p":"eɡəʊmə'naɪəklɪ","t":"adv. 极端利己地"},"egomaniacs":"n. 极端利己主义者, 极端自我主义者, 自大狂( egomaniac的复数形式 )","egon":{"w":"Egon","t":"埃贡（人名）"},"egophonic":"[医] 羊音的","egophony":"[医] 羊音","egor":"abbr. experimental gas-cooled reactor 实验用气冷式反应堆","egos":{"p":"ˈeɡəuz","t":"n. 自我, 自尊, 自负( ego的复数形式 )"},"egosyntonic":"[医] 自我协调的","egotictic":"以自我为中心的,任性的","egotism":{"p":"'egәutizm","t":"n. 自我中心癖, 自负\\n[医] 利己主义, 唯我主义"},"egotist":{"p":"'egәutist","t":"n. 自我中心主义者"},"egotistic":{"p":".egәu'tistik","t":"a. 自我本位的, 自负的"},"egotistical":{"p":".egәu'tistikәl","t":"a. 自我本位的, 自负的"},"egotistically":"adv. egotistic, egotistical的变形","egotists":"n. 自我中心主义者( egotist的复数形式 )","egotize":{"p":"'egәutaiz","t":"vi. 过分强调自我"},"egotized":{"p":"'eɡətaɪz","t":"vi. 过分强调自我"},"egotizing":{"p":"'eɡətaɪz","t":"vi. 过分强调自我"},"egotrip":{"p":"'i:^әjtrip,'e^-","t":"vi.追名逐利,自私地行事, 表现自己"},"egotripping":{"p":"'i:ɡəutripiŋ","t":"n. 自我陶醉行为, 自感优越行为"},"egotropic":"[医] 自我中心的","egp":{"w":"EGP","t":"[计] 外部网关路由协议, 外部网关协议"},"egpyt":"n. 埃及","egr":"[医][=erythema gyratum repens]（拉）匐行性回状红斑","egranulose":{"p":"eɡrænjʊ'ləʊs","t":"[医]无小颗粒的"},"egre":{"p":"'i:ɡri:","t":"涨潮"},"egregious":{"p":"i'gri:dʒiәs","t":"a. 异乎寻常的, 过分的, 惊人的"},"egregiously":{"p":"ɪɡ'ri:dʒɪəəslɪ","t":"adv. 过份地, 卓越地"},"egregiousness":"过份","egregorsis":"[医] 熟睡不能, 酣睡不能","egremont":"[人名] 埃格雷蒙特; [地名] [加拿大、英国] 埃格勒蒙特","egress":{"p":"'i:gres","t":"n. 出口, 外出\\nvi. 外出"},"egressed":"n. 出口, 外出\\nvi. 外出","egresses":{"p":"'iːgres","t":"n. 外出；出口\\nvi. 外出\\nvt. 使外出"},"egressing":"n. 出口, 外出\\nvi. 外出","egression":{"p":"i:'greʃәn","t":"n. 外出"},"egret":{"p":"'i:gret","t":"n. 白鹭"},"egrets":"(egret 的复数) n. 白鹭","egretta":{"w":"Egretta","t":"[网络] 白鹭属；飘兵鲂鮄"},"egri":"[医][=enterogastric reflux index]胃肠回流指数","egrp":"abbr. exterior gateway routing protocol 外部网关路由协议","egs":"(eg 的复数) abbr. [拉]例如（exempli gratia）；[网络用语]邪恶的笑（Evil Grin）","egta":{"w":"EGTA","t":"[化] 乙二醇双(2-氨基乙醚)四乙酸"},"egtism":"自负","egu":"abbr. English Golf Union <英国>英格兰高尔夫球联合会","egueite":"球磷钙铁矿","eguttulate":{"p":"i'^ʌtjjleit,-lit","t":"a. 无斑点的"},"egypt":{"w":"Egypt","p":"'i:dʒipt","t":"n. 埃及"},"egyptair":"埃及航空公司","egyptian":{"w":"Egyptian","p":"i'dʒipʃәn","t":"n. 埃及人\\na. 埃及的, 埃及人的"},"egyptianism":{"w":"Egyptianism","p":"i'dʒipʃәnizәm","t":"n. 埃及之特征, 埃及人之特征"},"egyptianization":{"w":"Egyptianization","p":"i,dʒipʃәnai'zeiʃәn;-ni'z-","t":"n. 埃及化"},"egyptianize":{"w":"Egyptianize","p":"i'dʒipʃәnaiz","t":"v. 使埃及化"},"egyptians":"n. 埃及人","egyptological":{"p":"i,dʒiptə'lɔdʒikəl","t":"a. Egyptology的变形"},"egyptologist":{"w":"Egyptologist","p":"i:dʒip'tɒlәdʒist","t":"n. 埃及文物学者"},"egyptologists":{"w":"Egyptologists","t":"(Egyptologist 的复数) n. 埃及文物学者"},"egyptology":{"w":"Egyptology","p":"i:dʒip'tɒlәdʒi","t":"n. 埃及文物学"}}