{"pg":{"w":"PG","t":"部分不适合儿童观看的(电影)\\n[化] 前列腺素; 磷脂酰甘油"},"pga":"abbr. 美国职业高尔夫球协会（Professional Golfer' Association of America）","pgas":"[医][=polyglandular autoimmune syndrome]多（内分泌）腺性自身免疫综合征","pgc":{"w":"PGC","t":"abbr. 专业生成内容(Professional Generated Content), 是专业的内容设置及产品内容编辑\\nabbr. 程序增益控制 ( programmed gain control)"},"pgce":{"p":"ˌpi: dʒi: si: ˈi:","t":"n. Postgraduate Certificate of Education 教育学研究生证书; a course of study that you do after getting a university degree so that you can teach in a state school; the qualification you get when you have completed a PGCE course"},"pgces":"(pgce 的复数) n. Postgraduate Certificate of Education 教育学研究生证书; a course of study that you do after getting a university degree so that you can teach in a state school; the qualification you get when you have completed a PGCE course","pgd":{"p":"'pi:dʒ'i:d'i:","t":"[医][=hydroxy-prostaglandin dehydrogenase]羟基前列腺素脱氢酶"},"pgdn":"向下翻页键","pge":{"w":"PGE","t":"abbr. 前列腺素e（phenyl glycidyl ether）"},"pgi":{"p":"p'ɡɪ","t":"[医][=(serum)pepsinogen i]（血浆）胃蛋白酶元？（放免测定）"},"pgknolepsy":"[医] 癫痫小发作","pgl":"abbr. puppy beagle 小狗，小猎犬","pgm":"abbr. 精密制导武器（precision-guided munition）","pgms":"abbr. propyelene glycol monostearate 丙二醇-硬脂酸酯","pgns":"abbr. Primary Guidance and Navigation System 初级制导与导航系统","pgp":"abbr. 加密软体（Pretty Good Privacy）","pgps":" [计]= Pulse Groups Per Second,脉冲组/秒","pgs":{"p":"'pi:dʒ'i:'es","t":"abbr. predicted ground speed 预测地面速度"},"pgt":{"p":"'pi:dʒ'i:t'i:","t":"[医][=15-hydroxy prostaglandin dehydrogenase]15-羟前列腺素脱氢酶"},"pgthisiogenesis":"[医] 痨病发生, 成痨","pgup":"n. 页上移键(Page Up的缩写)","pgx":"[医][=prostaglandin X]前列腺素X","pgy":"abbr. postgraduate year 研究生年度"}